I2C_controller/i2c_slave.v
    /*
I2C Slave

Input:
    SCL:            Serial Clock
    SDA:            Serial DATA
    slave_addr:     Slave Address
    slave_reg_addr: Slave Register Address
    rst:            Async Reset
*/

module I2C_Slave(
    input clk,
    input SCL,
    inout SDA,
    input[6:0] slave_addr,
    input rst                       // Async Reset
);  

    // Generation of START/STOP/Data Valid Signal
    reg[2:0] data_state,data_next_state;
    parameter IDLE=3'd0, ValidData1=3'd1, ValidData0=3'd2, START=3'd3, STOP=3'd4;
    always@(posedge clk or posedge rst) begin
        if(rst) data_state <= IDLE;
        else data_state <= (SCL) ? data_next_state : IDLE;
    end
    always@(*) begin
        case(data_state)
            IDLE:       data_next_state = (SDA_control) ? IDLE : SDA_input ? ValidData1 : ValidData0;
            ValidData1: data_next_state = (SDA_control) ? IDLE : SDA_input ? ValidData1 : START;
            ValidData0: data_next_state = (SDA_control) ? IDLE : SDA_input ? STOP : ValidData0;
            default:    data_next_state = (SDA_control) ? IDLE : data_next_state;
        endcase
    end

    wire start_sign, stop_sign;
    assign start_sign = (data_state == START) ? 1'b1:1'b0;
    assign stop_sign = (data_state == STOP) ? 1'b1:1'b0;

    reg start_received, stop_received;
    always@(*) start_received <= (SCL) ? start_sign : start_received;
    always@(*) stop_received <= (SCL) ? stop_sign : stop_received;

    // I2C Data Register
    reg[7:0] data_reg;
    always@(posedge SCL or posedge rst) data_reg <= (rst) ? 8'd0 : {data_reg[6:0],SDA_input};

    // I2C FSM
    reg[7:0] i2c_state, i2c_next_state;
    parameter INIT=0,ADDR6=1,ADDR5=2,ADDR4=3,ADDR3=4,ADDR2=5,ADDR1=6,ADDR0=7;
    parameter RW_t=8,ACK1=9,WAIT=10,REG_ADDR7=11,REG_ADDR0=18;
    parameter ACK2=19,DATA7=20,DATA6=21,DATA0=27,ACK3=28,ACK4=29;
    parameter DATA_OUT7=30,DATA_OUT6=31,DATA_OUT5=32,DATA_OUT4=33,DATA_OUT3=34,DATA_OUT2=35,DATA_OUT1=36,DATA_OUT0=37,NACK=38;

    always@(negedge SCL or posedge rst) begin
        if(rst) i2c_state <= INIT;
        else i2c_state <= i2c_next_state;
    end
    always@(*) begin
        case(i2c_state)
            INIT:       i2c_next_state = start_received ? ADDR6 : INIT;
            RW_t:       i2c_next_state = (data_reg[7:1] == slave_addr) ? ((data_reg[0]==1'b0) ? ACK1 : ACK4) : WAIT;
            WAIT:       i2c_next_state = stop_received ? INIT : WAIT;
            ACK1:       i2c_next_state = REG_ADDR7;
            ACK2:       i2c_next_state = DATA7;
            DATA7:      i2c_next_state = (start_received) ? ADDR6 : ((stop_received) ? INIT : DATA6);
            ACK3:       i2c_next_state = DATA7;
            ACK4:       i2c_next_state = DATA_OUT7;
            DATA_OUT0:  i2c_next_state = NACK;
            NACK:       i2c_next_state = (data_reg[0]) ? WAIT:DATA_OUT7;
            default :   i2c_next_state = i2c_state + 1'd1;
        endcase
    end

    // SDA Output / ACK Handling
    reg SDA_output,SDA_input;
    reg[7:0] output_reg;
    wire SDA_control;
    assign SDA_control = ((i2c_state == ACK1)|(i2c_state == ACK2)|(i2c_state == ACK3)|(i2c_state == ACK4)|((i2c_state >= DATA_OUT7) & (i2c_state <= DATA_OUT0))) ? 1'b1:1'b0;
    assign SDA = (SDA_control) ? SDA_output : 1'bz;
    always@(*) SDA_input = (SDA_control) ? 1'b1 : SDA;
    always@(*) output_reg = data_memory[addr_reg];
    always@(*) begin
        case(i2c_state)
            ACK1:       SDA_output = 1'b0;
            ACK2:       SDA_output = 1'b0;
            ACK3:       SDA_output = 1'b0;
            ACK4:       SDA_output = 1'b0;
            DATA_OUT7:  SDA_output = output_reg[7];
            DATA_OUT6:  SDA_output = output_reg[6];
            DATA_OUT5:  SDA_output = output_reg[5];
            DATA_OUT4:  SDA_output = output_reg[4];
            DATA_OUT3:  SDA_output = output_reg[3];
            DATA_OUT2:  SDA_output = output_reg[2];
            DATA_OUT1:  SDA_output = output_reg[1];
            DATA_OUT0:  SDA_output = output_reg[0];
            default:    SDA_output = 1'b1;
        endcase
    end

    // DATA IO
    reg[7:0][7:0] data_memory;
    reg[7:0] addr_reg;
    wire acquire_data_address;

    always@(posedge rst) data_memory <= 64'h0;
    assign acquire_data_address = (i2c_state == ACK2)|(i2c_state == DATA7)|(i2c_state == NACK) ? 1'b1 : 1'b0;
    always@(posedge acquire_data_address or posedge rst) begin
        if(rst) addr_reg <= 8'd0;
        else addr_reg <= (i2c_state == ACK2) ? data_reg : (i2c_state == DATA7)|(i2c_state == NACK) ? addr_reg+7'h1 : addr_reg;
    end

    always@(*) data_memory[addr_reg] = (i2c_state == DATA0) ? data_reg :data_memory[addr_reg];

endmodule

I2C_controller/i2c_tb.v
`timescale 1ns/1ns

`include "i2c_slave.v"

module tb_top();
    
    reg SCL,SDA_r,rst,enable,clk;
    reg data_recv_enable;
    reg[7:0] data_received;
    always #5 SCL <= ~SCL;
    always #1 clk <= ~clk;
    assign SDA = (enable) ? SDA_r : 1'bz;
    
    always@(posedge SCL or posedge rst) data_received <= (rst) ? 8'd0 : ~enable ? {data_received[6:0],SDA} : data_received;

    task SEND_START(input[6:0] addr,input RW);
        begin
            enable = 1'b1; SDA_r = 1'b1;
            #4; SDA_r = 0; #6;      // START
            SDA_r = addr[6]; #10;     // ADDR6
            SDA_r = addr[5]; #10;     // ADDR5
            SDA_r = addr[4]; #10;     // ADDR4
            SDA_r = addr[3]; #10;     // ADDR3
            SDA_r = addr[2]; #10;     // ADDR2
            SDA_r = addr[1]; #10;     // ADDR1
            SDA_r = addr[0]; #10;     // ADDR0
            SDA_r = RW; #5;     // RW
            enable = 1'b0; SDA_r = 1'b1; #10;
            enable = 1'b1; SDA_r = 1'b1;
        end
    endtask

    task SEND_START_AGAIN(input[6:0] addr,input RW);
        begin
            $display("Sending START Signal at ",$time);
            enable = 1'b1; SDA_r = 1'b1;
            #9; SDA_r = 0; #6;      // START
            SDA_r = addr[6]; #10;     // ADDR6
            SDA_r = addr[5]; #10;     // ADDR5
            SDA_r = addr[4]; #10;     // ADDR4
            SDA_r = addr[3]; #10;     // ADDR3
            SDA_r = addr[2]; #10;     // ADDR2
            SDA_r = addr[1]; #10;     // ADDR1
            SDA_r = addr[0]; #10;     // ADDR0
            SDA_r = RW; #5;     // RW
            enable = 1'b0; SDA_r = 1'b1; #10;
            enable = 1'b1; SDA_r = 1'b1;
        end
    endtask

    task SEND_REG_ADDR(input[7:0] addr);
        begin
            enable = 1'b1; SDA_r = 1'b1;
            SDA_r = addr[7]; #10;     // ADDR7
            SDA_r = addr[6]; #10;     // ADDR6
            SDA_r = addr[5]; #10;     // ADDR5
            SDA_r = addr[4]; #10;     // ADDR4
            SDA_r = addr[3]; #10;     // ADDR3
            SDA_r = addr[2]; #10;     // ADDR2
            SDA_r = addr[1]; #10;     // ADDR1
            SDA_r = addr[0]; #10;     // ADDR0
            enable = 1'b0; SDA_r = 1'b1; #10;enable = 1'b1; SDA_r = 1'b1;
        end
    endtask

    task SEND_BYTE_DATA(input[7:0] addr);
        begin
            enable = 1'b1; SDA_r = 1'b1;
            SDA_r = addr[7]; #10;     // DATA
            SDA_r = addr[6]; #10;     // DATA
            SDA_r = addr[5]; #10;     // DATA
            SDA_r = addr[4]; #10;     // DATA
            SDA_r = addr[3]; #10;     // DATA
            SDA_r = addr[2]; #10;     // DATA
            SDA_r = addr[1]; #10;     // DATA
            SDA_r = addr[0]; #10;     // DATA
            enable = 1'b0; SDA_r = 1'b1; #10;enable = 1'b1; SDA_r = 1'b1;
        end
    endtask

    task SEND_STOP();
        begin
            $display($time);
            enable = 1'b1;SDA_r = 0; #8;
            SDA_r = 1; #7;
        end
    endtask

    task WAIT_DATA(input ACK);
        begin
            data_recv_enable = 1;
            enable = 0; SDA_r = 1'b1;#80;
            data_recv_enable = 0;
            enable = 1; SDA_r = ACK; #10;
        end
    endtask

    initial begin
        $dumpfile("tb_wave.vcd");
        $dumpvars(0, tb_top);
        rst = 1; SCL = 1'b1; clk=1'b1; SDA_r = 1; enable = 0; data_recv_enable = 0; #7;
        rst = 0; enable = 1; #13;

        SEND_START(6'h11,1'b0);
        SEND_REG_ADDR(8'h00);

        SEND_BYTE_DATA(8'h00);
        SEND_BYTE_DATA(8'h11);
        SEND_BYTE_DATA(8'h22);
        SEND_BYTE_DATA(8'h33);
        SEND_BYTE_DATA(8'h44);
        SEND_BYTE_DATA(8'h55);
        SEND_BYTE_DATA(8'h66);
        SEND_BYTE_DATA(8'h77);
        SEND_STOP();
        
        //enable = 1; SDA_r = 1;
        SEND_START(6'h11,1'b0);
        SEND_REG_ADDR(8'h03);

        data_recv_enable = 1;

        SEND_START_AGAIN(6'h11,1'b1);
        WAIT_DATA(1'b1);
        SEND_STOP();#100;
        $finish;
    end


    I2C_Slave slave0(clk,SCL,SDA,7'h11,rst);
endmodule

I2C_controller/tb_wave.vcd
$date
	Wed Nov 29 09:38:38 2023
$end
$version
	Icarus Verilog
$end
$timescale
	1ns
$end
$scope module tb_top $end
$var wire 1 ! SDA $end
$var reg 1 " SCL $end
$var reg 1 # SDA_r $end
$var reg 1 $ clk $end
$var reg 8 % data_received [7:0] $end
$var reg 1 & data_recv_enable $end
$var reg 1 ' enable $end
$var reg 1 ( rst $end
$scope module slave0 $end
$var wire 1 " SCL $end
$var wire 1 ! SDA $end
$var wire 1 $ clk $end
$var wire 1 ( rst $end
$var wire 7 ) slave_addr [6:0] $end
$var wire 1 * stop_sign $end
$var wire 1 + start_sign $end
$var wire 1 , acquire_data_address $end
$var wire 1 - SDA_control $end
$var parameter 32 . ACK1 $end
$var parameter 32 / ACK2 $end
$var parameter 32 0 ACK3 $end
$var parameter 32 1 ACK4 $end
$var parameter 32 2 ADDR0 $end
$var parameter 32 3 ADDR1 $end
$var parameter 32 4 ADDR2 $end
$var parameter 32 5 ADDR3 $end
$var parameter 32 6 ADDR4 $end
$var parameter 32 7 ADDR5 $end
$var parameter 32 8 ADDR6 $end
$var parameter 32 9 DATA0 $end
$var parameter 32 : DATA6 $end
$var parameter 32 ; DATA7 $end
$var parameter 32 < DATA_OUT0 $end
$var parameter 32 = DATA_OUT1 $end
$var parameter 32 > DATA_OUT2 $end
$var parameter 32 ? DATA_OUT3 $end
$var parameter 32 @ DATA_OUT4 $end
$var parameter 32 A DATA_OUT5 $end
$var parameter 32 B DATA_OUT6 $end
$var parameter 32 C DATA_OUT7 $end
$var parameter 3 D IDLE $end
$var parameter 32 E INIT $end
$var parameter 32 F NACK $end
$var parameter 32 G REG_ADDR0 $end
$var parameter 32 H REG_ADDR7 $end
$var parameter 32 I RW_t $end
$var parameter 3 J START $end
$var parameter 3 K STOP $end
$var parameter 3 L ValidData0 $end
$var parameter 3 M ValidData1 $end
$var parameter 32 N WAIT $end
$var reg 1 O SDA_input $end
$var reg 1 P SDA_output $end
$var reg 8 Q addr_reg [7:0] $end
$var reg 64 R data_memory [63:0] $end
$var reg 3 S data_next_state [2:0] $end
$var reg 8 T data_reg [7:0] $end
$var reg 3 U data_state [2:0] $end
$var reg 8 V i2c_next_state [7:0] $end
$var reg 8 W i2c_state [7:0] $end
$var reg 8 X output_reg [7:0] $end
$var reg 1 Y start_received $end
$var reg 1 Z stop_received $end
$upscope $end
$scope task SEND_BYTE_DATA $end
$var reg 8 [ addr [7:0] $end
$upscope $end
$scope task SEND_REG_ADDR $end
$var reg 8 \ addr [7:0] $end
$upscope $end
$scope task SEND_START $end
$var reg 1 ] RW $end
$var reg 7 ^ addr [6:0] $end
$upscope $end
$scope task SEND_START_AGAIN $end
$var reg 1 _ RW $end
$var reg 7 ` addr [6:0] $end
$upscope $end
$scope task SEND_STOP $end
$upscope $end
$scope task WAIT_DATA $end
$var reg 1 a ACK $end
$upscope $end
$upscope $end
$enddefinitions $end
$comment Show the parameter values. $end
$dumpall
b1010 N
b1 M
b10 L
b100 K
b11 J
b1000 I
b1011 H
b10010 G
b100110 F
b0 E
b0 D
b11110 C
b11111 B
b100000 A
b100001 @
b100010 ?
b100011 >
b100100 =
b100101 <
b10100 ;
b10101 :
b11011 9
b1 8
b10 7
b11 6
b100 5
b101 4
b110 3
b111 2
b11101 1
b11100 0
b10011 /
b1001 .
$end
#0
$dumpvars
xa
bx `
x_
bx ^
x]
bx \
bx [
0Z
0Y
b0 X
b0 W
b0 V
b0 U
b0 T
b0xx S
b0 R
b0 Q
1P
zO
0-
0,
0+
0*
b10001 )
1(
0'
0&
b0 %
1$
1#
1"
z!
$end
#1
0$
#2
1$
#3
0$
#4
1$
#5
0$
0"
#6
1$
#7
0$
b1 S
1O
1!
1'
0(
#8
1$
#9
0$
#10
b1 U
b1 T
1$
1"
#11
0$
#12
1$
#13
0$
#14
1$
#15
0$
0"
#16
b0 U
1$
#17
0$
#18
1$
#19
0$
#20
b1 U
b11 T
1$
1"
0]
b10001 ^
#21
0$
#22
1$
#23
0$
#24
b1 V
1Y
1+
b11 U
1$
b11 S
0O
0!
0#
#25
b10 V
b1 W
0$
0"
#26
b10 S
0+
b0 U
1$
#27
0$
#28
1$
#29
0$
#30
b10 U
b110 T
0Y
1$
1"
#31
0$
#32
1$
#33
0$
#34
1$
#35
b11 V
b10 W
0$
0"
#36
b0 U
1$
#37
0$
#38
1$
#39
0$
#40
b10 U
b1100 T
1$
1"
#41
0$
#42
1$
#43
0$
#44
1$
#45
b100 V
b11 W
0$
0"
#46
b0 U
1$
#47
0$
#48
1$
#49
0$
#50
b1 U
b11001 T
1$
1"
b1 S
1O
1!
1#
#51
0$
#52
1$
#53
0$
#54
1$
#55
b101 V
b100 W
0$
0"
#56
b0 U
1$
#57
0$
#58
1$
#59
0$
#60
b10 U
b110010 T
1$
1"
b10 S
0O
0!
0#
#61
0$
#62
1$
#63
0$
#64
1$
#65
b110 V
b101 W
0$
0"
#66
b0 U
1$
#67
0$
#68
1$
#69
0$
#70
b10 U
b1100100 T
1$
1"
#71
0$
#72
1$
#73
0$
#74
1$
#75
b111 V
b110 W
0$
0"
#76
b0 U
1$
#77
0$
#78
1$
#79
0$
#80
b10 U
b11001000 T
1$
1"
#81
0$
#82
1$
#83
0$
#84
1$
#85
b1000 V
b111 W
0$
0"
#86
b0 U
1$
#87
0$
#88
1$
#89
0$
#90
b1 U
b10010001 T
1$
1"
b1 S
1O
1!
1#
#91
0$
#92
1$
#93
0$
#94
1$
#95
b1010 V
b1000 W
0$
0"
#96
b0 U
1$
#97
0$
#98
1$
#99
0$
#100
b1001 V
b10 U
b100010 T
1$
1"
b10 S
0O
0!
0#
#101
0$
#102
1$
#103
0$
#104
1$
#105
1-
0P
b1011 V
b1001 W
0$
0"
b0 S
1O
0!
1#
0'
#106
b0 U
1$
#107
0$
#108
1$
#109
0$
#110
b1000101 T
1$
1"
#111
0$
#112
1$
#113
0$
#114
1$
#115
0O
b10 S
0-
0!
1P
b1100 V
b1011 W
0$
0"
0#
b0 \
1'
#116
1$
#117
0$
#118
1$
#119
0$
#120
b10 U
b10001010 T
1$
1"
#121
0$
#122
1$
#123
0$
#124
1$
#125
b1101 V
b1100 W
0$
0"
#126
b0 U
1$
#127
0$
#128
1$
#129
0$
#130
b10 U
b10100 T
1$
1"
#131
0$
#132
1$
#133
0$
#134
1$
#135
b1110 V
b1101 W
0$
0"
#136
b0 U
1$
#137
0$
#138
1$
#139
0$
#140
b10 U
b101000 T
1$
1"
#141
0$
#142
1$
#143
0$
#144
1$
#145
b1111 V
b1110 W
0$
0"
#146
b0 U
1$
#147
0$
#148
1$
#149
0$
#150
b10 U
b1010000 T
1$
1"
#151
0$
#152
1$
#153
0$
#154
1$
#155
b10000 V
b1111 W
0$
0"
#156
b0 U
1$
#157
0$
#158
1$
#159
0$
#160
b10 U
b10100000 T
1$
1"
#161
0$
#162
1$
#163
0$
#164
1$
#165
b10001 V
b10000 W
0$
0"
#166
b0 U
1$
#167
0$
#168
1$
#169
0$
#170
b10 U
b1000000 T
1$
1"
#171
0$
#172
1$
#173
0$
#174
1$
#175
b10010 V
b10001 W
0$
0"
#176
b0 U
1$
#177
0$
#178
1$
#179
0$
#180
b10 U
b10000000 T
1$
1"
#181
0$
#182
1$
#183
0$
#184
1$
#185
b10011 V
b10010 W
0$
0"
#186
b0 U
1$
#187
0$
#188
1$
#189
0$
#190
b10 U
b0 T
1$
1"
#191
0$
#192
1$
#193
0$
#194
1$
#195
1-
1,
0P
b10100 V
b10011 W
0$
0"
b0 S
1O
0!
1#
0'
#196
b0 U
1$
#197
0$
#198
1$
#199
0$
#200
b1 T
1$
1"
#201
0$
#202
1$
#203
0$
#204
1$
#205
0O
b10 S
0-
0!
1P
b10101 V
b10100 W
0$
0"
0#
b0 [
1'
#206
1$
#207
0$
#208
1$
#209
0$
#210
b10 U
b10 T
1$
1"
#211
0$
#212
1$
#213
0$
#214
1$
#215
0,
b10110 V
b10101 W
0$
0"
#216
b0 U
1$
#217
0$
#218
1$
#219
0$
#220
b10 U
b100 T
1$
1"
#221
0$
#222
1$
#223
0$
#224
1$
#225
b10111 V
b10110 W
0$
0"
#226
b0 U
1$
#227
0$
#228
1$
#229
0$
#230
b10 U
b1000 T
1$
1"
#231
0$
#232
1$
#233
0$
#234
1$
#235
b11000 V
b10111 W
0$
0"
#236
b0 U
1$
#237
0$
#238
1$
#239
0$
#240
b10 U
b10000 T
1$
1"
#241
0$
#242
1$
#243
0$
#244
1$
#245
b11001 V
b11000 W
0$
0"
#246
b0 U
1$
#247
0$
#248
1$
#249
0$
#250
b10 U
b100000 T
1$
1"
#251
0$
#252
1$
#253
0$
#254
1$
#255
b11010 V
b11001 W
0$
0"
#256
b0 U
1$
#257
0$
#258
1$
#259
0$
#260
b10 U
b1000000 T
1$
1"
#261
0$
#262
1$
#263
0$
#264
1$
#265
b11011 V
b11010 W
0$
0"
#266
b0 U
1$
#267
0$
#268
1$
#269
0$
#270
b10 U
b10000000 T
1$
1"
#271
0$
#272
1$
#273
0$
#274
1$
#275
b10000000 X
b10000000 R
b11100 V
b11011 W
0$
0"
#276
b0 U
1$
#277
0$
#278
1$
#279
0$
#280
b0 X
b0 R
b10 U
b0 T
1$
1"
#281
0$
#282
1$
#283
0$
#284
1$
#285
1-
0P
b10100 V
b11100 W
0$
0"
b0 S
1O
0!
1#
0'
#286
b0 U
1$
#287
0$
#288
1$
#289
0$
#290
b1 T
1$
1"
#291
0$
#292
1$
#293
0$
#294
1$
#295
b1 Q
0O
b10 S
0-
1,
0!
1P
b10101 V
b10100 W
0$
0"
0#
b10001 [
1'
#296
1$
#297
0$
#298
1$
#299
0$
#300
b10 U
b10 T
1$
1"
#301
0$
#302
1$
#303
0$
#304
1$
#305
0,
b10110 V
b10101 W
0$
0"
#306
b0 U
1$
#307
0$
#308
1$
#309
0$
#310
b10 U
b100 T
1$
1"
#311
0$
#312
1$
#313
0$
#314
1$
#315
b10111 V
b10110 W
0$
0"
#316
b0 U
1$
#317
0$
#318
1$
#319
0$
#320
b10 U
b1000 T
1$
1"
#321
0$
#322
1$
#323
0$
#324
1$
#325
b11000 V
b10111 W
0$
0"
b100 S
1O
1!
1#
#326
b1 S
b0 U
1$
#327
0$
#328
1$
#329
0$
#330
b1 U
b10001 T
1$
1"
#331
0$
#332
1$
#333
0$
#334
1$
#335
b11001 V
b11000 W
0$
0"
b11 S
0O
0!
0#
#336
b10 S
b0 U
1$
#337
0$
#338
1$
#339
0$
#340
b10 U
b100010 T
1$
1"
#341
0$
#342
1$
#343
0$
#344
1$
#345
b11010 V
b11001 W
0$
0"
#346
b0 U
1$
#347
0$
#348
1$
#349
0$
#350
b10 U
b1000100 T
1$
1"
#351
0$
#352
1$
#353
0$
#354
1$
#355
b11011 V
b11010 W
0$
0"
#356
b0 U
1$
#357
0$
#358
1$
#359
0$
#360
b10 U
b10001000 T
1$
1"
#361
0$
#362
1$
#363
0$
#364
1$
#365
b10001000 X
b1000100000000000 R
b11100 V
b11011 W
0$
0"
b100 S
1O
1!
1#
#366
b1 S
b0 U
1$
#367
0$
#368
1$
#369
0$
#370
b10001 X
b1000100000000 R
b1 U
b10001 T
1$
1"
#371
0$
#372
1$
#373
0$
#374
1$
#375
1-
0P
b10100 V
b11100 W
0$
0"
b0 S
1O
0!
0'
#376
b0 U
1$
#377
0$
#378
1$
#379
0$
#380
b100011 T
1$
1"
#381
0$
#382
1$
#383
0$
#384
1$
#385
b0 X
b10 Q
0O
b10 S
0-
1,
0!
1P
b10101 V
b10100 W
0$
0"
0#
b100010 [
1'
#386
1$
#387
0$
#388
1$
#389
0$
#390
b10 U
b1000110 T
1$
1"
#391
0$
#392
1$
#393
0$
#394
1$
#395
0,
b10110 V
b10101 W
0$
0"
#396
b0 U
1$
#397
0$
#398
1$
#399
0$
#400
b10 U
b10001100 T
1$
1"
#401
0$
#402
1$
#403
0$
#404
1$
#405
b10111 V
b10110 W
0$
0"
b100 S
1O
1!
1#
#406
b1 S
b0 U
1$
#407
0$
#408
1$
#409
0$
#410
b1 U
b11001 T
1$
1"
#411
0$
#412
1$
#413
0$
#414
1$
#415
b11000 V
b10111 W
0$
0"
b11 S
0O
0!
0#
#416
b10 S
b0 U
1$
#417
0$
#418
1$
#419
0$
#420
b10 U
b110010 T
1$
1"
#421
0$
#422
1$
#423
0$
#424
1$
#425
b11001 V
b11000 W
0$
0"
#426
b0 U
1$
#427
0$
#428
1$
#429
0$
#430
b10 U
b1100100 T
1$
1"
#431
0$
#432
1$
#433
0$
#434
1$
#435
b11010 V
b11001 W
0$
0"
#436
b0 U
1$
#437
0$
#438
1$
#439
0$
#440
b10 U
b11001000 T
1$
1"
#441
0$
#442
1$
#443
0$
#444
1$
#445
b11011 V
b11010 W
0$
0"
b100 S
1O
1!
1#
#446
b1 S
b0 U
1$
#447
0$
#448
1$
#449
0$
#450
b1 U
b10010001 T
1$
1"
#451
0$
#452
1$
#453
0$
#454
1$
#455
b10010001 X
b100100010001000100000000 R
b11100 V
b11011 W
0$
0"
b11 S
0O
0!
0#
#456
b10 S
b0 U
1$
#457
0$
#458
1$
#459
0$
#460
b100010 X
b1000100001000100000000 R
b10 U
b100010 T
1$
1"
#461
0$
#462
1$
#463
0$
#464
1$
#465
1-
0P
b10100 V
b11100 W
0$
0"
b0 S
1O
0!
1#
0'
#466
b0 U
1$
#467
0$
#468
1$
#469
0$
#470
b1000101 T
1$
1"
#471
0$
#472
1$
#473
0$
#474
1$
#475
b0 X
b11 Q
0O
b10 S
0-
1,
0!
1P
b10101 V
b10100 W
0$
0"
0#
b110011 [
1'
#476
1$
#477
0$
#478
1$
#479
0$
#480
b10 U
b10001010 T
1$
1"
#481
0$
#482
1$
#483
0$
#484
1$
#485
0,
b10110 V
b10101 W
0$
0"
#486
b0 U
1$
#487
0$
#488
1$
#489
0$
#490
b10 U
b10100 T
1$
1"
#491
0$
#492
1$
#493
0$
#494
1$
#495
b10111 V
b10110 W
0$
0"
b100 S
1O
1!
1#
#496
b1 S
b0 U
1$
#497
0$
#498
1$
#499
0$
#500
b1 U
b101001 T
1$
1"
#501
0$
#502
1$
#503
0$
#504
1$
#505
b11000 V
b10111 W
0$
0"
#506
b0 U
1$
#507
0$
#508
1$
#509
0$
#510
b1 U
b1010011 T
1$
1"
#511
0$
#512
1$
#513
0$
#514
1$
#515
b11001 V
b11000 W
0$
0"
b11 S
0O
0!
0#
#516
b10 S
b0 U
1$
#517
0$
#518
1$
#519
0$
#520
b10 U
b10100110 T
1$
1"
#521
0$
#522
1$
#523
0$
#524
1$
#525
b11010 V
b11001 W
0$
0"
#526
b0 U
1$
#527
0$
#528
1$
#529
0$
#530
b10 U
b1001100 T
1$
1"
#531
0$
#532
1$
#533
0$
#534
1$
#535
b11011 V
b11010 W
0$
0"
b100 S
1O
1!
1#
#536
b1 S
b0 U
1$
#537
0$
#538
1$
#539
0$
#540
b1 U
b10011001 T
1$
1"
#541
0$
#542
1$
#543
0$
#544
1$
#545
b10011001 X
b10011001001000100001000100000000 R
b11100 V
b11011 W
0$
0"
#546
b0 U
1$
#547
0$
#548
1$
#549
0$
#550
b110011 X
b110011001000100001000100000000 R
b1 U
b110011 T
1$
1"
#551
0$
#552
1$
#553
0$
#554
1$
#555
1-
0P
b10100 V
b11100 W
0$
0"
b0 S
1O
0!
0'
#556
b0 U
1$
#557
0$
#558
1$
#559
0$
#560
b1100111 T
1$
1"
#561
0$
#562
1$
#563
0$
#564
1$
#565
b0 X
b100 Q
0O
b10 S
0-
1,
0!
1P
b10101 V
b10100 W
0$
0"
0#
b1000100 [
1'
#566
1$
#567
0$
#568
1$
#569
0$
#570
b10 U
b11001110 T
1$
1"
#571
0$
#572
1$
#573
0$
#574
1$
#575
0,
b10110 V
b10101 W
0$
0"
b100 S
1O
1!
1#
#576
b1 S
b0 U
1$
#577
0$
#578
1$
#579
0$
#580
b1 U
b10011101 T
1$
1"
#581
0$
#582
1$
#583
0$
#584
1$
#585
b10111 V
b10110 W
0$
0"
b11 S
0O
0!
0#
#586
b10 S
b0 U
1$
#587
0$
#588
1$
#589
0$
#590
b10 U
b111010 T
1$
1"
#591
0$
#592
1$
#593
0$
#594
1$
#595
b11000 V
b10111 W
0$
0"
#596
b0 U
1$
#597
0$
#598
1$
#599
0$
#600
b10 U
b1110100 T
1$
1"
#601
0$
#602
1$
#603
0$
#604
1$
#605
b11001 V
b11000 W
0$
0"
#606
b0 U
1$
#607
0$
#608
1$
#609
0$
#610
b10 U
b11101000 T
1$
1"
#611
0$
#612
1$
#613
0$
#614
1$
#615
b11010 V
b11001 W
0$
0"
b100 S
1O
1!
1#
#616
b1 S
b0 U
1$
#617
0$
#618
1$
#619
0$
#620
b1 U
b11010001 T
1$
1"
#621
0$
#622
1$
#623
0$
#624
1$
#625
b11011 V
b11010 W
0$
0"
b11 S
0O
0!
0#
#626
b10 S
b0 U
1$
#627
0$
#628
1$
#629
0$
#630
b10 U
b10100010 T
1$
1"
#631
0$
#632
1$
#633
0$
#634
1$
#635
b10100010 X
b1010001000110011001000100001000100000000 R
b11100 V
b11011 W
0$
0"
#636
b0 U
1$
#637
0$
#638
1$
#639
0$
#640
b1000100 X
b100010000110011001000100001000100000000 R
b10 U
b1000100 T
1$
1"
#641
0$
#642
1$
#643
0$
#644
1$
#645
1-
0P
b10100 V
b11100 W
0$
0"
b0 S
1O
0!
1#
0'
#646
b0 U
1$
#647
0$
#648
1$
#649
0$
#650
b10001001 T
1$
1"
#651
0$
#652
1$
#653
0$
#654
1$
#655
b0 X
b101 Q
0O
b10 S
0-
1,
0!
1P
b10101 V
b10100 W
0$
0"
0#
b1010101 [
1'
#656
1$
#657
0$
#658
1$
#659
0$
#660
b10 U
b10010 T
1$
1"
#661
0$
#662
1$
#663
0$
#664
1$
#665
0,
b10110 V
b10101 W
0$
0"
b100 S
1O
1!
1#
#666
b1 S
b0 U
1$
#667
0$
#668
1$
#669
0$
#670
b1 U
b100101 T
1$
1"
#671
0$
#672
1$
#673
0$
#674
1$
#675
b10111 V
b10110 W
0$
0"
b11 S
0O
0!
0#
#676
b10 S
b0 U
1$
#677
0$
#678
1$
#679
0$
#680
b10 U
b1001010 T
1$
1"
#681
0$
#682
1$
#683
0$
#684
1$
#685
b11000 V
b10111 W
0$
0"
b100 S
1O
1!
1#
#686
b1 S
b0 U
1$
#687
0$
#688
1$
#689
0$
#690
b1 U
b10010101 T
1$
1"
#691
0$
#692
1$
#693
0$
#694
1$
#695
b11001 V
b11000 W
0$
0"
b11 S
0O
0!
0#
#696
b10 S
b0 U
1$
#697
0$
#698
1$
#699
0$
#700
b10 U
b101010 T
1$
1"
#701
0$
#702
1$
#703
0$
#704
1$
#705
b11010 V
b11001 W
0$
0"
b100 S
1O
1!
1#
#706
b1 S
b0 U
1$
#707
0$
#708
1$
#709
0$
#710
b1 U
b1010101 T
1$
1"
#711
0$
#712
1$
#713
0$
#714
1$
#715
b11011 V
b11010 W
0$
0"
b11 S
0O
0!
0#
#716
b10 S
b0 U
1$
#717
0$
#718
1$
#719
0$
#720
b10 U
b10101010 T
1$
1"
#721
0$
#722
1$
#723
0$
#724
1$
#725
b10101010 X
b101010100100010000110011001000100001000100000000 R
b11100 V
b11011 W
0$
0"
b100 S
1O
1!
1#
#726
b1 S
b0 U
1$
#727
0$
#728
1$
#729
0$
#730
b1010101 X
b10101010100010000110011001000100001000100000000 R
b1 U
b1010101 T
1$
1"
#731
0$
#732
1$
#733
0$
#734
1$
#735
1-
0P
b10100 V
b11100 W
0$
0"
b0 S
1O
0!
0'
#736
b0 U
1$
#737
0$
#738
1$
#739
0$
#740
b10101011 T
1$
1"
#741
0$
#742
1$
#743
0$
#744
1$
#745
b0 X
b110 Q
0O
b10 S
0-
1,
0!
1P
b10101 V
b10100 W
0$
0"
0#
b1100110 [
1'
#746
1$
#747
0$
#748
1$
#749
0$
#750
b10 U
b1010110 T
1$
1"
#751
0$
#752
1$
#753
0$
#754
1$
#755
0,
b10110 V
b10101 W
0$
0"
b100 S
1O
1!
1#
#756
b1 S
b0 U
1$
#757
0$
#758
1$
#759
0$
#760
b1 U
b10101101 T
1$
1"
#761
0$
#762
1$
#763
0$
#764
1$
#765
b10111 V
b10110 W
0$
0"
#766
b0 U
1$
#767
0$
#768
1$
#769
0$
#770
b1 U
b1011011 T
1$
1"
#771
0$
#772
1$
#773
0$
#774
1$
#775
b11000 V
b10111 W
0$
0"
b11 S
0O
0!
0#
#776
b10 S
b0 U
1$
#777
0$
#778
1$
#779
0$
#780
b10 U
b10110110 T
1$
1"
#781
0$
#782
1$
#783
0$
#784
1$
#785
b11001 V
b11000 W
0$
0"
#786
b0 U
1$
#787
0$
#788
1$
#789
0$
#790
b10 U
b1101100 T
1$
1"
#791
0$
#792
1$
#793
0$
#794
1$
