I2C_controller/i2c_slave.v
    /*
I2C Slave

Input:
    SCL:            Serial Clock
    SDA:            Serial DATA
    slave_addr:     Slave Address
    slave_reg_addr: Slave Register Address
    rst:            Async Reset
*/

module I2C_Slave(
    input clk,
    input SCL,
    inout SDA,
    input[6:0] slave_addr,
    input[7:0] slave_reg_addr,
    input rst                       // Async Reset
);  

    // Generation of START/STOP/Data Valid Signal
    reg[2:0] data_state,data_next_state;
    parameter IDLE=3'd0, ValidData1=3'd1, ValidData0=3'd2, START=3'd3, STOP=3'd4;
    always@(posedge clk or posedge rst) begin
        if(rst) data_state <= IDLE;
        else data_state <= (SCL) ? data_next_state : IDLE;
    end
    always@(*) begin
        case(data_state)
            IDLE:       data_next_state = SDA ? ValidData1 : ValidData0;
            ValidData1: data_next_state = SDA ? ValidData1 : START;
            ValidData0: data_next_state = SDA ? STOP : ValidData0;
            default:    data_next_state = data_next_state;
        endcase
    end

    wire start_sign, stop_sign;
    assign start_sign = (data_state == START) ? 1'b1:1'b0;
    assign stop_sign = (data_state == STOP) ? 1'b1:1'b0;

    reg start_received, stop_received;
    always@(*) start_received <= (SCL) ? start_sign : start_received;
    always@(*) stop_received <= (SCL) ? stop_sign : stop_received;

    // I2C Data Register
    reg[7:0] data_reg;
    always@(posedge SCL or posedge rst) data_reg <= (rst) ? 8'd0 : {data_reg[6:0],SDA};

    // I2C FSM
    reg[7:0] i2c_state, i2c_next_state;
    parameter INIT=0,ADDR6=1,ADDR5=2,ADDR4=3,ADDR3=4,ADDR2=5,ADDR1=6,ADDR0=7;
    parameter RW_t=8,ACK1=9,WAIT=10,REG_ADDR7=11,REG_ADDR0=18;
    parameter ACK2=19,DATA7=20,DATA6=21,DATA0=27,ACK3=28,ACK4=29;
    parameter DATA_OUT7=30,DATA_OUT6=31,DATA_OUT5=32,DATA_OUT4=33,DATA_OUT3=34,DATA_OUT2=35,DATA_OUT1=36,DATA_OUT0=37,NACK=38;

    always@(posedge SCL or posedge rst) begin
        if(rst) i2c_state <= INIT;
        else i2c_state <= i2c_next_state;
    end
    always@(*) begin
        case(i2c_state)
            INIT:       i2c_next_state = start_received ? ADDR6 : INIT;
            RW_t:       i2c_next_state = (data_reg[7:1] == slave_addr) ? ((data_reg[0]==1'b0) ? ACK1 : ACK4) : WAIT;
            WAIT:       i2c_next_state = stop_received ? INIT : WAIT;
            ACK1:       i2c_next_state = REG_ADDR7;
            ACK2:       i2c_next_state = DATA7;
            DATA7:      i2c_next_state = (start_received) ? ADDR6 : ((stop_received) ? INIT : DATA6);
            ACK3:       i2c_next_state = DATA7;
            ACK4:       i2c_next_state = DATA_OUT7;
            DATA_OUT0:  i2c_next_state = (SDA) ? NACK : ACK4;
            NACK:       i2c_next_state = WAIT;
            default :   i2c_next_state = i2c_state + 1'd1;
        endcase
    end

    // SDA Output / ACK Handling
    reg SDA_output;
    reg[7:0] output_reg;
    wire SDA_control;
    assign SDA_control = ((i2c_state == ACK1)|(i2c_state == ACK2)|(i2c_state == ACK3)|(i2c_state == ACK4)|((i2c_state >= DATA_OUT7) & (i2c_state <= DATA_OUT0))) ? 1'b1:1'b0;
    assign SDA = (SDA_control) ? SDA_output : 1'bz;
    always@(*) output_reg = data_memory[addr_reg];
    always@(*) begin
        case(i2c_state)
            ACK1:       SDA_output = 1'b0;
            ACK2:       SDA_output = 1'b0;
            ACK3:       SDA_output = 1'b0;
            ACK4:       SDA_output = 1'b0;
            DATA_OUT7:  SDA_output = output_reg[7];
            DATA_OUT6:  SDA_output = output_reg[6];
            DATA_OUT5:  SDA_output = output_reg[5];
            DATA_OUT4:  SDA_output = output_reg[4];
            DATA_OUT3:  SDA_output = output_reg[3];
            DATA_OUT2:  SDA_output = output_reg[2];
            DATA_OUT1:  SDA_output = output_reg[1];
            DATA_OUT0:  SDA_output = output_reg[0];
            default:    SDA_output = 1'b1;
        endcase
    end

    // DATA IO
    reg[7:0][3:0] data_memory;
    reg[7:0] addr_reg;
    wire acquire_data_address;

    always@(posedge rst) data_memory <= 32'h0;
    assign acquire_data_address = (i2c_state == ACK2)|(i2c_state == DATA7) ? 1'b1 : 1'b0;
    always@(posedge acquire_data_address or posedge rst) begin
        if(rst) addr_reg <= 8'd0;
        else addr_reg <= (i2c_state == ACK2) ? data_reg : (i2c_state == DATA7) ? addr_reg+1'b1 : addr_reg;
    end

    always@(*) data_memory[addr_reg] = (i2c_state == DATA0) ? data_reg :data_memory[addr_reg];

endmodule

I2C_controller/i2c_tb.v
`timescale 1ns/1ns

`include "i2c_slave.v"

module tb_top();
    
    reg SCL,SDA_r,rst,enable,clk;
    always #5 SCL <= ~SCL;
    always #1 clk <= ~clk;
    assign SDA = (enable) ? SDA_r : 1'bz;
    
    task SEND_START(input[6:0] addr,input RW);
        begin
            #4; SDA_r = 0; #6;      // START
            SDA_r = addr[6]; #10;     // ADDR6
            SDA_r = addr[5]; #10;     // ADDR5
            SDA_r = addr[4]; #10;     // ADDR4
            SDA_r = addr[3]; #10;     // ADDR3
            SDA_r = addr[2]; #10;     // ADDR2
            SDA_r = addr[1]; #10;     // ADDR1
            SDA_r = addr[0]; #10;     // ADDR0
            SDA_r = RW; #10;     // RW
            enable = 1'b0; SDA_r = 1'b1; #10;enable = 1'b1;
        end
    endtask

    task SEND_REG_ADDR(input[7:0] addr);
        begin
            SDA_r = addr[7]; #10;     // ADDR7
            SDA_r = addr[6]; #10;     // ADDR6
            SDA_r = addr[5]; #10;     // ADDR5
            SDA_r = addr[4]; #10;     // ADDR4
            SDA_r = addr[3]; #10;     // ADDR3
            SDA_r = addr[2]; #10;     // ADDR2
            SDA_r = addr[1]; #10;     // ADDR1
            SDA_r = addr[0]; #10;     // ADDR0
            enable = 1'b0; SDA_r = 1'b1; #10;enable = 1'b1;
        end
    endtask

    task SEND_BYTE_DATA(input[7:0] addr);
        begin
            SDA_r = addr[7]; #10;     // DATA
            SDA_r = addr[6]; #10;     // DATA
            SDA_r = addr[5]; #10;     // DATA
            SDA_r = addr[4]; #10;     // DATA
            SDA_r = addr[3]; #10;     // DATA
            SDA_r = addr[2]; #10;     // DATA
            SDA_r = addr[1]; #10;     // DATA
            SDA_r = addr[0]; #10;     // DATA
            enable = 1'b0; SDA_r = 1'b1; #10;enable = 1'b1;
        end
    endtask

    task SEND_STOP();
        begin
            SDA_r = 0; #3;
            SDA_r = 1; #7;
        end
    endtask

    initial begin
        $dumpfile("tb_wave.vcd");
        $dumpvars(0, tb_top);
        rst = 1; SCL = 1'b1; clk=1'b1; SDA_r = 1; enable = 0; #7;
        rst = 0; enable = 1; #12;

        SEND_START(6'h11,1'b0);
        SEND_REG_ADDR(8'h0);
        SEND_BYTE_DATA(8'h1);
        SEND_BYTE_DATA(8'h2);
        SEND_BYTE_DATA(8'h3);
        SEND_BYTE_DATA(8'h4);
        SEND_BYTE_DATA(8'h5);
        SEND_BYTE_DATA(8'h6);
        SEND_BYTE_DATA(8'h7);
        SEND_BYTE_DATA(8'h8);
        SEND_STOP();
        #100;
        SEND_START(6'h11,1'b0);
        SEND_REG_ADDR(8'h5);
        SEND_START(6'h11,1'b1);
        //SEND_REG_ADDR(8'h0);
        enable = 0;#100;
        $finish;
    end

    I2C_Slave slave0(clk,SCL,SDA,7'h11,8'h00,rst);

endmodule

I2C_controller/tb_wave.vcd
$date
	Thu Nov 23 13:57:31 2023
$end
$version
	Icarus Verilog
$end
$timescale
	1ns
$end
$scope module tb_top $end
$var wire 1 ! SDA $end
$var reg 1 " SCL $end
$var reg 1 # SDA_r $end
$var reg 1 $ clk $end
$var reg 1 % enable $end
$var reg 1 & rst $end
$scope module slave0 $end
$var wire 1 " SCL $end
$var wire 1 ! SDA $end
$var wire 1 $ clk $end
$var wire 1 & rst $end
$var wire 7 ' slave_addr [6:0] $end
$var wire 8 ( slave_reg_addr [7:0] $end
$var wire 1 ) stop_sign $end
$var wire 1 * start_sign $end
$var wire 1 + acquire_data_address $end
$var wire 1 , SDA_control $end
$var parameter 32 - ACK1 $end
$var parameter 32 . ACK2 $end
$var parameter 32 / ACK3 $end
$var parameter 32 0 ACK4 $end
$var parameter 32 1 ADDR0 $end
$var parameter 32 2 ADDR1 $end
$var parameter 32 3 ADDR2 $end
$var parameter 32 4 ADDR3 $end
$var parameter 32 5 ADDR4 $end
$var parameter 32 6 ADDR5 $end
$var parameter 32 7 ADDR6 $end
$var parameter 32 8 DATA0 $end
$var parameter 32 9 DATA6 $end
$var parameter 32 : DATA7 $end
$var parameter 32 ; DATA_OUT0 $end
$var parameter 32 < DATA_OUT1 $end
$var parameter 32 = DATA_OUT2 $end
$var parameter 32 > DATA_OUT3 $end
$var parameter 32 ? DATA_OUT4 $end
$var parameter 32 @ DATA_OUT5 $end
$var parameter 32 A DATA_OUT6 $end
$var parameter 32 B DATA_OUT7 $end
$var parameter 3 C IDLE $end
$var parameter 32 D INIT $end
$var parameter 32 E NACK $end
$var parameter 32 F REG_ADDR0 $end
$var parameter 32 G REG_ADDR7 $end
$var parameter 32 H RW_t $end
$var parameter 3 I START $end
$var parameter 3 J STOP $end
$var parameter 3 K ValidData0 $end
$var parameter 3 L ValidData1 $end
$var parameter 32 M WAIT $end
$var reg 1 N SDA_output $end
$var reg 8 O addr_reg [7:0] $end
$var reg 32 P data_memory [31:0] $end
$var reg 3 Q data_next_state [2:0] $end
$var reg 8 R data_reg [7:0] $end
$var reg 3 S data_state [2:0] $end
$var reg 8 T i2c_next_state [7:0] $end
$var reg 8 U i2c_state [7:0] $end
$var reg 8 V output_reg [7:0] $end
$var reg 1 W start_received $end
$var reg 1 X stop_received $end
$upscope $end
$scope task SEND_BYTE_DATA $end
$var reg 8 Y addr [7:0] $end
$upscope $end
$scope task SEND_REG_ADDR $end
$var reg 8 Z addr [7:0] $end
$upscope $end
$scope task SEND_START $end
$var reg 1 [ RW $end
$var reg 7 \ addr [6:0] $end
$upscope $end
$scope task SEND_STOP $end
$upscope $end
$upscope $end
$enddefinitions $end
$comment Show the parameter values. $end
$dumpall
b1010 M
b1 L
b10 K
b100 J
b11 I
b1000 H
b1011 G
b10010 F
b100110 E
b0 D
b0 C
b11110 B
b11111 A
b100000 @
b100001 ?
b100010 >
b100011 =
b100100 <
b100101 ;
b10100 :
b10101 9
b11011 8
b1 7
b10 6
b11 5
b100 4
b101 3
b110 2
b111 1
b11101 0
b11100 /
b10011 .
b1001 -
$end
#0
$dumpvars
bx \
x[
bx Z
bx Y
0X
0W
b0 V
b0 U
b0 T
b0 S
b0 R
b0xx Q
b0 P
b0 O
1N
0,
0+
0*
0)
b0 (
b10001 '
1&
0%
1$
1#
1"
z!
$end
#1
0$
#2
1$
#3
0$
#4
1$
#5
0$
0"
#6
1$
#7
0$
b1 Q
1!
1%
0&
#8
1$
#9
0$
#10
b1 S
b1 R
1$
1"
#11
0$
#12
1$
#13
0$
#14
1$
#15
0$
0"
#16
b0 S
1$
#17
0$
#18
1$
#19
0$
0[
b10001 \
#20
b1 S
b11 R
1$
1"
#21
0$
#22
1$
#23
0$
b11 Q
0!
0#
#24
b1 T
1W
1*
b11 S
1$
#25
0$
0"
#26
b10 Q
0*
b0 S
1$
#27
0$
#28
1$
#29
0$
#30
b10 T
b10 S
b1 U
b110 R
0W
1$
1"
#31
0$
#32
1$
#33
0$
#34
1$
#35
0$
0"
#36
b0 S
1$
#37
0$
#38
1$
#39
0$
#40
b11 T
b10 S
b1100 R
b10 U
1$
1"
#41
0$
#42
1$
#43
0$
#44
1$
#45
0$
0"
#46
b0 S
1$
#47
0$
#48
1$
#49
0$
b1 Q
1!
1#
#50
b100 T
b1 S
b11 U
b11001 R
1$
1"
#51
0$
#52
1$
#53
0$
#54
1$
#55
0$
0"
#56
b0 S
1$
#57
0$
#58
1$
#59
0$
b10 Q
0!
0#
#60
b101 T
b10 S
b110010 R
b100 U
1$
1"
#61
0$
#62
1$
#63
0$
#64
1$
#65
0$
0"
#66
b0 S
1$
#67
0$
#68
1$
#69
0$
#70
b110 T
b10 S
b101 U
b1100100 R
1$
1"
#71
0$
#72
1$
#73
0$
#74
1$
#75
0$
0"
#76
b0 S
1$
#77
0$
#78
1$
#79
0$
#80
b111 T
b10 S
b11001000 R
b110 U
1$
1"
#81
0$
#82
1$
#83
0$
#84
1$
#85
0$
0"
#86
b0 S
1$
#87
0$
#88
1$
#89
0$
b1 Q
1!
1#
#90
b1000 T
b1 S
b111 U
b10010001 R
1$
1"
#91
0$
#92
1$
#93
0$
#94
1$
#95
0$
0"
#96
b0 S
1$
#97
0$
#98
1$
#99
0$
b10 Q
0!
0#
#100
b1001 T
b10 S
b100010 R
b1000 U
1$
1"
#101
0$
#102
1$
#103
0$
#104
1$
#105
0$
0"
#106
b0 S
1$
#107
0$
#108
1$
#109
0$
b0xx Q
z!
1#
0%
#110
xW
0!
1,
x*
0N
b1011 T
b0xx S
b1001 U
b100010z R
1$
1"
#111
0$
#112
1$
#113
0$
#114
1$
#115
0$
0"
#116
b10 Q
0*
b0 S
1$
#117
0$
#118
1$
#119
0$
0#
b0 Z
1%
#120
0,
b10 Q
0!
1N
b1100 T
b10 S
b100010z0 R
b1011 U
0W
1$
1"
#121
0$
#122
1$
#123
0$
#124
1$
#125
0$
0"
#126
b0 S
1$
#127
0$
#128
1$
#129
0$
#130
b1101 T
b10 S
b1100 U
b10z00 R
1$
1"
#131
0$
#132
1$
#133
0$
#134
1$
#135
0$
0"
#136
b0 S
1$
#137
0$
#138
1$
#139
0$
#140
b1110 T
b10 S
b10z000 R
b1101 U
1$
1"
#141
0$
#142
1$
#143
0$
#144
1$
#145
0$
0"
#146
b0 S
1$
#147
0$
#148
1$
#149
0$
#150
b1111 T
b10 S
b1110 U
b10z0000 R
1$
1"
#151
0$
#152
1$
#153
0$
#154
1$
#155
0$
0"
#156
b0 S
1$
#157
0$
#158
1$
#159
0$
#160
b10000 T
b10 S
b10z00000 R
b1111 U
1$
1"
#161
0$
#162
1$
#163
0$
#164
1$
#165
0$
0"
#166
b0 S
1$
#167
0$
#168
1$
#169
0$
#170
b10001 T
b10 S
b10000 U
b0z000000 R
1$
1"
#171
0$
#172
1$
#173
0$
#174
1$
#175
0$
0"
#176
b0 S
1$
#177
0$
#178
1$
#179
0$
#180
b10010 T
b10 S
bz0000000 R
b10001 U
1$
1"
#181
0$
#182
1$
#183
0$
#184
1$
#185
0$
0"
#186
b0 S
1$
#187
0$
#188
1$
#189
0$
#190
b10011 T
b10 S
b10010 U
b0 R
1$
1"
#191
0$
#192
1$
#193
0$
#194
1$
#195
0$
0"
#196
b0 S
1$
#197
0$
#198
1$
#199
0$
b0xx Q
z!
1#
0%
#200
b0xxxx V
b0z O
xW
0!
1,
1+
x*
0N
b10100 T
b0xx S
b0z R
b10011 U
1$
1"
#201
0$
#202
1$
#203
0$
#204
1$
#205
0$
0"
#206
b10 Q
0*
b0 S
1$
#207
0$
#208
1$
#209
0$
0#
b1 Y
1%
#210
0,
b10 Q
0!
1N
b10101 T
b10 S
b10100 U
b0z0 R
0W
1$
1"
#211
0$
#212
1$
#213
0$
#214
1$
#215
0$
0"
#216
b0 S
1$
#217
0$
#218
1$
#219
0$
#220
0+
b10110 T
b10 S
b0z00 R
b10101 U
1$
1"
#221
0$
#222
1$
#223
0$
#224
1$
#225
0$
0"
#226
b0 S
1$
#227
0$
#228
1$
#229
0$
#230
b10111 T
b10 S
b10110 U
b0z000 R
1$
1"
#231
0$
#232
1$
#233
0$
#234
1$
#235
0$
0"
#236
b0 S
1$
#237
0$
#238
1$
#239
0$
#240
b11000 T
b10 S
b0z0000 R
b10111 U
1$
1"
#241
0$
#242
1$
#243
0$
#244
1$
#245
0$
0"
#246
b0 S
1$
#247
0$
#248
1$
#249
0$
#250
b11001 T
b10 S
b11000 U
b0z00000 R
1$
1"
#251
0$
#252
1$
#253
0$
#254
1$
#255
0$
0"
#256
b0 S
1$
#257
0$
#258
1$
#259
0$
#260
b11010 T
b10 S
b0z000000 R
b11001 U
1$
1"
#261
0$
#262
1$
#263
0$
#264
1$
#265
0$
0"
#266
b0 S
1$
#267
0$
#268
1$
#269
0$
#270
b11011 T
b10 S
b11010 U
bz0000000 R
1$
1"
#271
0$
#272
1$
#273
0$
#274
1$
#275
0$
0"
#276
b0 S
1$
#277
0$
#278
1$
#279
0$
b1 Q
1!
1#
#280
b11100 T
b1 S
b1 R
b11011 U
1$
1"
#281
0$
#282
1$
#283
0$
#284
1$
#285
0$
0"
#286
b0 S
1$
#287
0$
#288
1$
#289
0$
b0xx Q
z!
0%
#290
xW
0!
1,
x*
0N
b10100 T
b0xx S
b11100 U
b1z R
1$
1"
#291
0$
#292
1$
#293
0$
#294
1$
#295
0$
0"
#296
b10 Q
0*
b0 S
1$
#297
0$
#298
1$
#299
0$
0#
b10 Y
1%
#300
bx O
0,
b10 Q
0!
1+
1N
b10101 T
b10 S
b1z0 R
b10100 U
0W
1$
1"
#301
0$
#302
1$
#303
0$
#304
1$
#305
0$
0"
#306
b0 S
1$
#307
0$
#308
1$
#309
0$
#310
0+
b10110 T
b10 S
b10101 U
b1z00 R
1$
1"
#311
0$
#312
1$
#313
0$
#314
1$
#315
0$
0"
#316
b0 S
1$
#317
0$
#318
1$
#319
0$
#320
b10111 T
b10 S
b1z000 R
b10110 U
1$
1"
#321
0$
#322
1$
#323
0$
#324
1$
#325
0$
0"
#326
b0 S
1$
#327
0$
#328
1$
#329
0$
#330
b11000 T
b10 S
b10111 U
b1z0000 R
1$
1"
#331
0$
#332
1$
#333
0$
#334
1$
#335
0$
0"
#336
b0 S
1$
#337
0$
#338
1$
#339
0$
#340
b11001 T
b10 S
b1z00000 R
b11000 U
1$
1"
#341
0$
#342
1$
#343
0$
#344
1$
#345
0$
0"
#346
b0 S
1$
#347
0$
#348
1$
#349
0$
#350
b11010 T
b10 S
b11001 U
b1z000000 R
1$
1"
#351
0$
#352
1$
#353
0$
#354
1$
#355
0$
0"
#356
b0 S
1$
#357
0$
#358
1$
#359
0$
b1 Q
1!
1#
#360
b11011 T
b1 S
bz0000001 R
b11010 U
1$
1"
#361
0$
#362
1$
#363
0$
#364
1$
#365
0$
0"
#366
b0 S
1$
#367
0$
#368
1$
#369
0$
b10 Q
0!
0#
#370
b11100 T
b10 S
b11011 U
b10 R
1$
1"
#371
0$
#372
1$
#373
0$
#374
1$
#375
0$
0"
#376
b0 S
1$
#377
0$
#378
1$
#379
0$
b0xx Q
z!
1#
0%
#380
xW
0!
1,
x*
0N
b10100 T
b0xx S
b10z R
b11100 U
1$
1"
#381
0$
#382
1$
#383
0$
#384
1$
#385
0$
0"
#386
b10 Q
0*
b0 S
1$
#387
0$
#388
1$
#389
0$
0#
b11 Y
1%
#390
0,
b10 Q
0!
1+
1N
b10101 T
b10 S
b10100 U
b10z0 R
0W
1$
1"
#391
0$
#392
1$
#393
0$
#394
1$
#395
0$
0"
#396
b0 S
1$
#397
0$
#398
1$
#399
0$
#400
0+
b10110 T
b10 S
b10z00 R
b10101 U
1$
1"
#401
0$
#402
1$
#403
0$
#404
1$
#405
0$
0"
#406
b0 S
1$
#407
0$
#408
1$
#409
0$
#410
b10111 T
b10 S
b10110 U
b10z000 R
1$
1"
#411
0$
#412
1$
#413
0$
#414
1$
#415
0$
0"
#416
b0 S
1$
#417
0$
#418
1$
#419
0$
#420
b11000 T
b10 S
b10z0000 R
b10111 U
1$
1"
#421
0$
#422
1$
#423
0$
#424
1$
#425
0$
0"
#426
b0 S
1$
#427
0$
#428
1$
#429
0$
#430
b11001 T
b10 S
b11000 U
b10z00000 R
1$
1"
#431
0$
#432
1$
#433
0$
#434
1$
#435
0$
0"
#436
b0 S
1$
#437
0$
#438
1$
#439
0$
#440
b11010 T
b10 S
b0z000000 R
b11001 U
1$
1"
#441
0$
#442
1$
#443
0$
#444
1$
#445
0$
0"
#446
b0 S
1$
#447
0$
#448
1$
#449
0$
b1 Q
1!
1#
#450
b11011 T
b1 S
b11010 U
bz0000001 R
1$
1"
#451
0$
#452
1$
#453
0$
#454
1$
#455
0$
0"
#456
b0 S
1$
#457
0$
#458
1$
#459
0$
#460
b11100 T
b1 S
b11 R
b11011 U
1$
1"
#461
0$
#462
1$
#463
0$
#464
1$
#465
0$
0"
#466
b0 S
1$
#467
0$
#468
1$
#469
0$
b0xx Q
z!
0%
#470
xW
0!
1,
x*
0N
b10100 T
b0xx S
b11100 U
b11z R
1$
1"
#471
0$
#472
1$
#473
0$
#474
1$
#475
0$
0"
#476
b10 Q
0*
b0 S
1$
#477
0$
#478
1$
#479
0$
0#
b100 Y
1%
#480
0,
b10 Q
0!
1+
1N
b10101 T
b10 S
b11z0 R
b10100 U
0W
1$
1"
#481
0$
#482
1$
#483
0$
#484
1$
#485
0$
0"
#486
b0 S
1$
#487
0$
#488
1$
#489
0$
#490
0+
b10110 T
b10 S
b10101 U
b11z00 R
1$
1"
#491
0$
#492
1$
#493
0$
#494
1$
#495
0$
0"
#496
b0 S
1$
#497
0$
#498
1$
#499
0$
#500
b10111 T
b10 S
b11z000 R
b10110 U
1$
1"
#501
0$
#502
1$
#503
0$
#504
1$
#505
0$
0"
#506
b0 S
1$
#507
0$
#508
1$
#509
0$
#510
b11000 T
b10 S
b10111 U
b11z0000 R
1$
1"
#511
0$
#512
1$
#513
0$
#514
1$
#515
0$
0"
#516
b0 S
1$
#517
0$
#518
1$
#519
0$
#520
b11001 T
b10 S
b11z00000 R
b11000 U
1$
1"
#521
0$
#522
1$
#523
0$
#524
1$
#525
0$
0"
#526
b0 S
1$
#527
0$
#528
1$
#529
0$
b1 Q
1!
1#
#530
b11010 T
b1 S
b11001 U
b1z000001 R
1$
1"
#531
0$
#532
1$
#533
0$
#534
1$
#535
0$
0"
#536
b0 S
1$
#537
0$
#538
1$
#539
0$
b10 Q
0!
0#
#540
b11011 T
b10 S
bz0000010 R
b11010 U
1$
1"
#541
0$
#542
1$
#543
0$
#544
1$
#545
0$
0"
#546
b0 S
1$
#547
0$
#548
1$
#549
0$
#550
b11100 T
b10 S
b11011 U
b100 R
1$
1"
#551
0$
#552
1$
#553
0$
#554
1$
#555
0$
0"
#556
b0 S
1$
#557
0$
#558
1$
#559
0$
b0xx Q
z!
1#
0%
#560
xW
0!
1,
x*
0N
b10100 T
b0xx S
b100z R
b11100 U
1$
1"
#561
0$
#562
1$
#563
0$
#564
1$
#565
0$
0"
#566
b10 Q
0*
b0 S
1$
#567
0$
#568
1$
#569
0$
0#
b101 Y
1%
#570
0,
b10 Q
0!
1+
1N
b10101 T
b10 S
b10100 U
b100z0 R
0W
1$
1"
#571
0$
#572
1$
#573
0$
#574
1$
#575
0$
0"
#576
b0 S
1$
#577
0$
#578
1$
#579
0$
#580
0+
b10110 T
b10 S
b100z00 R
b10101 U
1$
1"
#581
0$
#582
1$
#583
0$
#584
1$
#585
0$
0"
#586
b0 S
1$
#587
0$
#588
1$
#589
0$
#590
b10111 T
b10 S
b10110 U
b100z000 R
1$
1"
#591
0$
#592
1$
#593
0$
#594
1$
#595
0$
0"
#596
b0 S
1$
#597
0$
#598
1$
#599
0$
#600
b11000 T
b10 S
b100z0000 R
b10111 U
1$
1"
#601
0$
#602
1$
#603
0$
#604
1$
#605
0$
0"
#606
b0 S
1$
#607
0$
#608
1$
#609
0$
#610
b11001 T
b10 S
b11000 U
b0z00000 R
1$
1"
#611
0$
#612
1$
#613
0$
#614
1$
#615
0$
0"
#616
b0 S
1$
#617
0$
#618
1$
#619
0$
b1 Q
1!
1#
#620
b11010 T
b1 S
b0z000001 R
b11001 U
1$
1"
#621
0$
#622
1$
#623
0$
#624
1$
#625
0$
0"
#626
b0 S
1$
#627
0$
#628
1$
#629
0$
b10 Q
0!
0#
#630
b11011 T
b10 S
b11010 U
bz0000010 R
1$
1"
#631
0$
#632
1$
#633
0$
#634
1$
#635
0$
0"
#636
b0 S
1$
#637
0$
#638
1$
#639
0$
b1 Q
1!
1#
#640
b11100 T
b1 S
b101 R
b11011 U
1$
1"
#641
0$
#642
1$
#643
0$
#644
1$
#645
0$
0"
#646
b0 S
1$
#647
0$
#648
1$
#649
0$
b0xx Q
z!
0%
#650
xW
0!
1,
x*
0N
b10100 T
b0xx S
b11100 U
b101z R
1$
1"
#651
0$
#652
1$
#653
0$
#654
1$
#655
0$
0"
#656
b10 Q
0*
b0 S
1$
#657
0$
#658
1$
#659
0$
0#
b110 Y
1%
#660
0,
b10 Q
0!
1+
1N
b10101 T
b10 S
b101z0 R
b10100 U
0W
1$
1"
#661
0$
#662
1$
#663
0$
#664
1$
#665
0$
0"
#666
b0 S
1$
#667
0$
#668
1$
#669
0$
#670
0+
b10110 T
b10 S
b10101 U
b101z00 R
1$
1"
#671
0$
#672
1$
#673
0$
#674
1$
#675
0$
0"
#676
b0 S
1$
#677
0$
#678
1$
#679
0$
#680
b10111 T
b10 S
b101z000 R
b10110 U
1$
1"
#681
0$
#682
1$
#683
0$
#684
1$
#685
0$
0"
#686
b0 S
1$
#687
0$
#688
1$
#689
0$
#690
b11000 T
b10 S
b10111 U
b101z0000 R
1$
1"
#691
0$
#692
1$
#693
0$
#694
1$
#695
0$
0"
#696
b0 S
1$
#697
0$
#698
1$
#699
0$
#700
b11001 T
b10 S
b1z00000 R
b11000 U
1$
1"
#701
0$
#702
1$
#703
0$
#704
1$
#705
0$
0"
#706
b0 S
1$
#707
0$
#708
1$
#709
0$
b1 Q
1!
1#
#710
b11010 T
b1 S
b11001 U
b1z000001 R
1$
1"
#711
0$
#712
1$
#713
0$
#714
1$
#715
0$
0"
#716
b0 S
1$
#717
0$
#718
1$
#719
0$
#720
b11011 T
b1 S
bz0000011 R
b11010 U
1$
1"
#721
0$
#722
1$
#723
0$
#724
1$
#725
0$
0"
#726
b0 S
1$
#727
0$
#728
1$
#729
0$
b10 Q
0!
0#
#730
b11100 T
b10 S
b11011 U
b110 R
1$
1"
#731
0$
#732
1$
#733
0$
#734
1$
#735
0$
0"
#736
b0 S
1$
#737
0$
#738
1$
#739
0$
b0xx Q
z!
1#
0%
#740
xW
0!
1,
x*
0N
b10100 T
b0xx S
b110z R
b11100 U
1$
1"
#741
0$
#742
1$
#743
0$
#744
1$
#745
0$
0"
#746
b10 Q
0*
b0 S
1$
#747
0$
#748
1$
#749
0$
0#
b111 Y
1%
#750
0,
b10 Q
0!
1+
1N
b10101 T
b10 S
b10100 U
b110z0 R
0W
1$
1"
#751
0$
#752
1$
#753
0$
#754
1$
#755
0$
0"
#756
b0 S
1$
#757
0$
#758
1$
#759
0$
#760
0+
b10110 T
b10 S
b110z00 R
b10101 U
1$
1"
#761
0$
#762
1$
#763
0$
#764
1$
#765
0$
0"
#766
b0 S
1$
#767
0$
#768
1$
#769
0$
#770
b10111 T
b10 S
b10110 U
b110z000 R
1$
1"
#771
0$
#772
1$
#773
0$
#774
1$
#775
0$
0"
#776
b0 S
1$
#777
0$
#778
1$
#779
0$
#780
b11000 T
b10 S
b110z0000 R
b10111 U
1$
1"
#781
0$
#782
1$
#783
0$
#784
1$
#785
0$
0"
#786
b0 S
1$
#787
0$
#788
1$
#789
0$
#790
b11001 T
b10 S
b11000 U
b10z00000 R
1$
1"
#791
0$
#792
1$
#793
0$
#794
1$
#795
0$
0"
#796
b0 S
1$
#797
0$
#798
1$
#799
0$
b1 Q
1!
1#
#800
b11010 T
b1 S
b0z000001 R
b11001 U
1$
1"
#801
0$
#802
1$
#803
0$
#804
1$
#805
0$
0"
#806
b0 S
1$
#807
0$
#808
1$
#809
0$
#810
b11011 T
b1 S
b11010 U
bz0000011 R
1$
1"
#811
0$
#812
1$
#813
0$
#814
1$
#815
0$
0"
#816
b0 S
1$
#817
0$
#818
1$
#819
0$
#820
b11100 T
b1 S
b111 R
b11011 U
1$
1"
#821
0$
#822
1$
#823
0$
#824
1$
#825
0$
0"
#826
b0 S
1$
#827
0$
#828
1$
#829
0$
b0xx Q
z!
0%
#830
xW
0!
1,
x*
0N
b10100 T
b0xx S
b11100 U
b111z R
1$
1"
#831
0$
#832
1$
#833
0$
#834
1$
#835
0$
0"
#836
b10 Q
0*
b0 S
1$
#837
0$
#838
1$
#839
0$
0#
b1000 Y
1%
#840
0,
b10 Q
0!
1+
1N
b10101 T
b10 S
b111z0 R
b10100 U
0W
1$
1"
#841
0$
#842
1$
#843
0$
#844
1$
#845
0$
0"
#846
b0 S
1$
#847
0$
#848
1$
#849
0$
#850
0+
b10110 T
b10 S
b10101 U
b111z00 R
1$
1"
#851
0$
#852
1$
#853
0$
#854
1$
#855
0$
0"
#856
b0 S
1$
#857
0$
#858
1$
#859
0$
#860
b10111 T
b10 S
b111z000 R
b10110 U
1$
1"
#861
0$
#862
1$
#863
0$
#864
1$
#865
0$
0"
#866
b0 S
1$
#867
0$
#868
1$
#869
0$
#870
b11000 T
b10 S
b10111 U
b111z0000 R
1$
1"
#871
0$
#872
1$
#873
0$
#874
1$
#875
0$
0"
#876
b0 S
1$
#877
0$
#878
1$
#879
0$
b1 Q
1!
1#
#880
b11001 T
b1 S
b11z00001 R
b11000 U
1$
1"
#881
0$
#882
1$
#883
0$
#884
1$
#885
0$
0"
#886
b0 S
1$
#887
0$
#888
1$
#889
0$
b10 Q
0!
0#
#890
b11010 T
b10 S
b11001 U
b1z000010 R
1$
1"
#891
0$
#892
1$
#893
0$
#894
1$
#895
0$
0"
#896
b0 S
1$
#897
0$
#898
1$
#899
0$
#900
b11011 T
b10 S
bz0000100 R
b11010 U
1$
1"
#901
0$
#902
1$
#903
0$
#904
1$
#905
0$
0"
#906
b0 S
1$
#907
0$
#908
1$
#909
0$
#910
b11100 T
b10 S
b11011 U
b1000 R
1$
1"
#911
0$
#912
1$
#913
0$
#914
1$
#915
0$
0"
#916
b0 S
1$
#917
0$
#918
1$
