MIPS_CPU/single_cycle/registers.v
module MIPS_registers (
    input clk,
    input we,
    input [4:0] rd_addr0_i,
    input [4:0] rd_addr1_i,
    input [4:0] wr_addr0_i,
    input [31:0] wr_data_i,
    output [31:0] rd_data0_o,
    output [31:0] rd_data1_o
);
    reg[31:0][31:0] register_files;
    
    always@(posedge clk) begin
        register_files[0] <= 32'h0;                                                 // $0 register always set to 0
        register_files[wr_addr0_i] <= we ? wr_data_i : register_files[wr_addr0_i];
    end

    assign rd_data0_o = register_files[rd_addr0_i];
    assign rd_data1_o = register_files[rd_addr1_i];

endmodule

MIPS_CPU/single_cycle/register_file_tb.v
`include "registers.v"
`timescale 1ns/1ps

module register_tb_top();

    reg clk, we;
    always #5 clk <= ~clk;
    always #20 wr_addr0_i <= wr_addr0_i + 1'b1;
    always #1 wr_data_i <= wr_data_i + 1'b1;

    reg[4:0] rd_addr0_i, rd_addr1_i, wr_addr0_i;
    wire[31:0] rd_data0_o,rd_data1_o;
    reg[31:0] wr_data_i;

    initial begin
        $dumpfile("register_file_tb.vcd");
        $dumpvars(0,register_tb_top);
        clk <= 1'b0;
        we <= 1'b1;
        wr_addr0_i <= 5'd0;
        wr_data_i <= 32'h0000_0000;

        wr_addr0_i <= 1'b1;
        #1000;
        $finish();
    end


    MIPS_registers register_file(clk,we,rd_addr0_i,rd_addr1_i,wr_addr0_i,wr_data_i,rd_data0_o,rd_data1_o);

endmodule

MIPS_CPU/single_cycle/register_file_tb.vcd
$date
	Wed Nov 29 23:43:47 2023
$end
$version
	Icarus Verilog
$end
$timescale
	1ps
$end
$scope module register_tb_top $end
$var wire 32 ! rd_data1_o [31:0] $end
$var wire 32 " rd_data0_o [31:0] $end
$var reg 1 # clk $end
$var reg 5 $ rd_addr0_i [4:0] $end
$var reg 5 % rd_addr1_i [4:0] $end
$var reg 1 & we $end
$var reg 5 ' wr_addr0_i [4:0] $end
$var reg 32 ( wr_data_i [31:0] $end
$scope module register_file $end
$var wire 1 # clk $end
$var wire 5 ) rd_addr0_i [4:0] $end
$var wire 5 * rd_addr1_i [4:0] $end
$var wire 1 & we $end
$var wire 5 + wr_addr0_i [4:0] $end
$var wire 32 , wr_data_i [31:0] $end
$var wire 32 - rd_data1_o [31:0] $end
$var wire 32 . rd_data0_o [31:0] $end
$var reg 1024 / register_files [1023:0] $end
$upscope $end
$upscope $end
$enddefinitions $end
$comment Show the parameter values. $end
$dumpall
$end
#0
$dumpvars
bx /
bx .
bx -
b0 ,
b1 +
bx *
bx )
b0 (
b1 '
1&
bx %
bx $
0#
bx "
bx !
$end
#1000
b1 (
b1 ,
#2000
b10 (
b10 ,
#3000
b11 (
b11 ,
#4000
b100 (
b100 ,
#5000
bx0000000000000000000000000000010100000000000000000000000000000000 /
b101 (
b101 ,
1#
#6000
b110 (
b110 ,
#7000
b111 (
b111 ,
#8000
b1000 (
b1000 ,
#9000
b1001 (
b1001 ,
#10000
b1010 (
b1010 ,
0#
#11000
b1011 (
b1011 ,
#12000
b1100 (
b1100 ,
#13000
b1101 (
b1101 ,
#14000
b1110 (
b1110 ,
#15000
bx0000000000000000000000000000111100000000000000000000000000000000 /
b1111 (
b1111 ,
1#
#16000
b10000 (
b10000 ,
#17000
b10001 (
b10001 ,
#18000
b10010 (
b10010 ,
#19000
b10011 (
b10011 ,
#20000
b10100 (
b10100 ,
0#
b10 '
b10 +
#21000
b10101 (
b10101 ,
#22000
b10110 (
b10110 ,
#23000
b10111 (
b10111 ,
#24000
b11000 (
b11000 ,
#25000
bx000000000000000000000000000110010000000000000000000000000000111100000000000000000000000000000000 /
b11001 (
b11001 ,
1#
#26000
b11010 (
b11010 ,
#27000
b11011 (
b11011 ,
#28000
b11100 (
b11100 ,
#29000
b11101 (
b11101 ,
#30000
b11110 (
b11110 ,
0#
#31000
b11111 (
b11111 ,
#32000
b100000 (
b100000 ,
#33000
b100001 (
b100001 ,
#34000
b100010 (
b100010 ,
#35000
bx000000000000000000000000001000110000000000000000000000000000111100000000000000000000000000000000 /
b100011 (
b100011 ,
1#
#36000
b100100 (
b100100 ,
#37000
b100101 (
b100101 ,
#38000
b100110 (
b100110 ,
#39000
b100111 (
b100111 ,
#40000
b101000 (
b101000 ,
0#
b11 '
b11 +
#41000
b101001 (
b101001 ,
#42000
b101010 (
b101010 ,
#43000
b101011 (
b101011 ,
#44000
b101100 (
b101100 ,
#45000
bx00000000000000000000000000101101000000000000000000000000001000110000000000000000000000000000111100000000000000000000000000000000 /
b101101 (
b101101 ,
1#
#46000
b101110 (
b101110 ,
#47000
b101111 (
b101111 ,
#48000
b110000 (
b110000 ,
#49000
b110001 (
b110001 ,
#50000
b110010 (
b110010 ,
0#
#51000
b110011 (
b110011 ,
#52000
b110100 (
b110100 ,
#53000
b110101 (
b110101 ,
#54000
b110110 (
b110110 ,
#55000
bx00000000000000000000000000110111000000000000000000000000001000110000000000000000000000000000111100000000000000000000000000000000 /
b110111 (
b110111 ,
1#
#56000
b111000 (
b111000 ,
#57000
b111001 (
b111001 ,
#58000
b111010 (
b111010 ,
#59000
b111011 (
b111011 ,
#60000
b111100 (
b111100 ,
0#
b100 '
b100 +
#61000
b111101 (
b111101 ,
#62000
b111110 (
b111110 ,
#63000
b111111 (
b111111 ,
#64000
b1000000 (
b1000000 ,
#65000
bx0000000000000000000000000100000100000000000000000000000000110111000000000000000000000000001000110000000000000000000000000000111100000000000000000000000000000000 /
b1000001 (
b1000001 ,
1#
#66000
b1000010 (
b1000010 ,
#67000
b1000011 (
b1000011 ,
#68000
b1000100 (
b1000100 ,
#69000
b1000101 (
b1000101 ,
#70000
b1000110 (
b1000110 ,
0#
#71000
b1000111 (
b1000111 ,
#72000
b1001000 (
b1001000 ,
#73000
b1001001 (
b1001001 ,
#74000
b1001010 (
b1001010 ,
#75000
bx0000000000000000000000000100101100000000000000000000000000110111000000000000000000000000001000110000000000000000000000000000111100000000000000000000000000000000 /
b1001011 (
b1001011 ,
1#
#76000
b1001100 (
b1001100 ,
#77000
b1001101 (
b1001101 ,
#78000
b1001110 (
b1001110 ,
#79000
b1001111 (
b1001111 ,
#80000
b1010000 (
b1010000 ,
0#
b101 '
b101 +
#81000
b1010001 (
b1010001 ,
#82000
b1010010 (
b1010010 ,
#83000
b1010011 (
b1010011 ,
#84000
b1010100 (
b1010100 ,
#85000
bx000000000000000000000000010101010000000000000000000000000100101100000000000000000000000000110111000000000000000000000000001000110000000000000000000000000000111100000000000000000000000000000000 /
b1010101 (
b1010101 ,
1#
#86000
b1010110 (
b1010110 ,
#87000
b1010111 (
b1010111 ,
#88000
b1011000 (
b1011000 ,
#89000
b1011001 (
b1011001 ,
#90000
b1011010 (
b1011010 ,
0#
#91000
b1011011 (
b1011011 ,
#92000
b1011100 (
b1011100 ,
#93000
b1011101 (
b1011101 ,
#94000
b1011110 (
b1011110 ,
#95000
bx000000000000000000000000010111110000000000000000000000000100101100000000000000000000000000110111000000000000000000000000001000110000000000000000000000000000111100000000000000000000000000000000 /
b1011111 (
b1011111 ,
1#
#96000
b1100000 (
b1100000 ,
#97000
b1100001 (
b1100001 ,
#98000
b1100010 (
b1100010 ,
#99000
b1100011 (
b1100011 ,
#100000
b1100100 (
b1100100 ,
0#
b110 '
b110 +
#101000
b1100101 (
b1100101 ,
#102000
b1100110 (
b1100110 ,
#103000
b1100111 (
b1100111 ,
#104000
b1101000 (
b1101000 ,
#105000
bx00000000000000000000000001101001000000000000000000000000010111110000000000000000000000000100101100000000000000000000000000110111000000000000000000000000001000110000000000000000000000000000111100000000000000000000000000000000 /
b1101001 (
b1101001 ,
1#
#106000
b1101010 (
b1101010 ,
#107000
b1101011 (
b1101011 ,
#108000
b1101100 (
b1101100 ,
#109000
b1101101 (
b1101101 ,
#110000
b1101110 (
b1101110 ,
0#
#111000
b1101111 (
b1101111 ,
#112000
b1110000 (
b1110000 ,
#113000
b1110001 (
b1110001 ,
#114000
b1110010 (
b1110010 ,
#115000
bx00000000000000000000000001110011000000000000000000000000010111110000000000000000000000000100101100000000000000000000000000110111000000000000000000000000001000110000000000000000000000000000111100000000000000000000000000000000 /
b1110011 (
b1110011 ,
1#
#116000
b1110100 (
b1110100 ,
#117000
b1110101 (
b1110101 ,
#118000
b1110110 (
b1110110 ,
#119000
b1110111 (
b1110111 ,
#120000
b1111000 (
b1111000 ,
0#
b111 '
b111 +
#121000
b1111001 (
b1111001 ,
#122000
b1111010 (
b1111010 ,
#123000
b1111011 (
b1111011 ,
#124000
b1111100 (
b1111100 ,
#125000
bx0000000000000000000000000111110100000000000000000000000001110011000000000000000000000000010111110000000000000000000000000100101100000000000000000000000000110111000000000000000000000000001000110000000000000000000000000000111100000000000000000000000000000000 /
b1111101 (
b1111101 ,
1#
#126000
b1111110 (
b1111110 ,
#127000
b1111111 (
b1111111 ,
#128000
b10000000 (
b10000000 ,
#129000
b10000001 (
b10000001 ,
#130000
b10000010 (
b10000010 ,
0#
#131000
b10000011 (
b10000011 ,
#132000
b10000100 (
b10000100 ,
#133000
b10000101 (
b10000101 ,
#134000
b10000110 (
b10000110 ,
#135000
bx0000000000000000000000001000011100000000000000000000000001110011000000000000000000000000010111110000000000000000000000000100101100000000000000000000000000110111000000000000000000000000001000110000000000000000000000000000111100000000000000000000000000000000 /
b10000111 (
b10000111 ,
1#
#136000
b10001000 (
b10001000 ,
#137000
b10001001 (
b10001001 ,
#138000
b10001010 (
b10001010 ,
#139000
b10001011 (
b10001011 ,
#140000
b10001100 (
b10001100 ,
0#
b1000 '
b1000 +
#141000
b10001101 (
b10001101 ,
#142000
b10001110 (
b10001110 ,
#143000
b10001111 (
b10001111 ,
#144000
b10010000 (
b10010000 ,
#145000
bx000000000000000000000000100100010000000000000000000000001000011100000000000000000000000001110011000000000000000000000000010111110000000000000000000000000100101100000000000000000000000000110111000000000000000000000000001000110000000000000000000000000000111100000000000000000000000000000000 /
b10010001 (
b10010001 ,
1#
#146000
b10010010 (
b10010010 ,
#147000
b10010011 (
b10010011 ,
#148000
b10010100 (
b10010100 ,
#149000
b10010101 (
b10010101 ,
#150000
b10010110 (
b10010110 ,
0#
#151000
b10010111 (
b10010111 ,
#152000
b10011000 (
b10011000 ,
#153000
b10011001 (
b10011001 ,
#154000
b10011010 (
b10011010 ,
#155000
bx000000000000000000000000100110110000000000000000000000001000011100000000000000000000000001110011000000000000000000000000010111110000000000000000000000000100101100000000000000000000000000110111000000000000000000000000001000110000000000000000000000000000111100000000000000000000000000000000 /
b10011011 (
b10011011 ,
1#
#156000
b10011100 (
b10011100 ,
#157000
b10011101 (
b10011101 ,
#158000
b10011110 (
b10011110 ,
#159000
b10011111 (
b10011111 ,
#160000
b10100000 (
b10100000 ,
0#
b1001 '
b1001 +
#161000
b10100001 (
b10100001 ,
#162000
b10100010 (
b10100010 ,
#163000
b10100011 (
b10100011 ,
#164000
b10100100 (
b10100100 ,
#165000
bx00000000000000000000000010100101000000000000000000000000100110110000000000000000000000001000011100000000000000000000000001110011000000000000000000000000010111110000000000000000000000000100101100000000000000000000000000110111000000000000000000000000001000110000000000000000000000000000111100000000000000000000000000000000 /
b10100101 (
b10100101 ,
1#
#166000
b10100110 (
b10100110 ,
#167000
b10100111 (
b10100111 ,
#168000
b10101000 (
b10101000 ,
#169000
b10101001 (
b10101001 ,
#170000
b10101010 (
b10101010 ,
0#
#171000
b10101011 (
b10101011 ,
#172000
b10101100 (
b10101100 ,
#173000
b10101101 (
b10101101 ,
#174000
b10101110 (
b10101110 ,
#175000
bx00000000000000000000000010101111000000000000000000000000100110110000000000000000000000001000011100000000000000000000000001110011000000000000000000000000010111110000000000000000000000000100101100000000000000000000000000110111000000000000000000000000001000110000000000000000000000000000111100000000000000000000000000000000 /
b10101111 (
b10101111 ,
1#
#176000
b10110000 (
b10110000 ,
#177000
b10110001 (
b10110001 ,
#178000
b10110010 (
b10110010 ,
#179000
b10110011 (
b10110011 ,
#180000
b10110100 (
b10110100 ,
0#
b1010 '
b1010 +
#181000
b10110101 (
b10110101 ,
#182000
b10110110 (
b10110110 ,
#183000
b10110111 (
b10110111 ,
#184000
b10111000 (
b10111000 ,
#185000
bx0000000000000000000000001011100100000000000000000000000010101111000000000000000000000000100110110000000000000000000000001000011100000000000000000000000001110011000000000000000000000000010111110000000000000000000000000100101100000000000000000000000000110111000000000000000000000000001000110000000000000000000000000000111100000000000000000000000000000000 /
b10111001 (
b10111001 ,
1#
#186000
b10111010 (
b10111010 ,
#187000
b10111011 (
b10111011 ,
#188000
b10111100 (
b10111100 ,
#189000
b10111101 (
b10111101 ,
#190000
b10111110 (
b10111110 ,
0#
#191000
b10111111 (
b10111111 ,
#192000
b11000000 (
b11000000 ,
#193000
b11000001 (
b11000001 ,
#194000
b11000010 (
b11000010 ,
#195000
bx0000000000000000000000001100001100000000000000000000000010101111000000000000000000000000100110110000000000000000000000001000011100000000000000000000000001110011000000000000000000000000010111110000000000000000000000000100101100000000000000000000000000110111000000000000000000000000001000110000000000000000000000000000111100000000000000000000000000000000 /
b11000011 (
b11000011 ,
1#
#196000
b11000100 (
b11000100 ,
#197000
b11000101 (
b11000101 ,
#198000
b11000110 (
b11000110 ,
#199000
b11000111 (
b11000111 ,
#200000
b11001000 (
b11001000 ,
0#
b1011 '
b1011 +
#201000
b11001001 (
b11001001 ,
#202000
b11001010 (
b11001010 ,
#203000
b11001011 (
b11001011 ,
#204000
b11001100 (
b11001100 ,
#205000
bx000000000000000000000000110011010000000000000000000000001100001100000000000000000000000010101111000000000000000000000000100110110000000000000000000000001000011100000000000000000000000001110011000000000000000000000000010111110000000000000000000000000100101100000000000000000000000000110111000000000000000000000000001000110000000000000000000000000000111100000000000000000000000000000000 /
b11001101 (
b11001101 ,
1#
#206000
b11001110 (
b11001110 ,
#207000
b11001111 (
b11001111 ,
#208000
b11010000 (
b11010000 ,
#209000
b11010001 (
b11010001 ,
#210000
b11010010 (
b11010010 ,
0#
#211000
b11010011 (
b11010011 ,
#212000
b11010100 (
b11010100 ,
#213000
b11010101 (
b11010101 ,
#214000
b11010110 (
b11010110 ,
#215000
bx000000000000000000000000110101110000000000000000000000001100001100000000000000000000000010101111000000000000000000000000100110110000000000000000000000001000011100000000000000000000000001110011000000000000000000000000010111110000000000000000000000000100101100000000000000000000000000110111000000000000000000000000001000110000000000000000000000000000111100000000000000000000000000000000 /
b11010111 (
b11010111 ,
1#
#216000
b11011000 (
b11011000 ,
#217000
b11011001 (
b11011001 ,
#218000
b11011010 (
b11011010 ,
#219000
b11011011 (
b11011011 ,
#220000
b11011100 (
b11011100 ,
0#
b1100 '
b1100 +
#221000
b11011101 (
b11011101 ,
#222000
b11011110 (
b11011110 ,
#223000
b11011111 (
b11011111 ,
#224000
b11100000 (
b11100000 ,
#225000
bx00000000000000000000000011100001000000000000000000000000110101110000000000000000000000001100001100000000000000000000000010101111000000000000000000000000100110110000000000000000000000001000011100000000000000000000000001110011000000000000000000000000010111110000000000000000000000000100101100000000000000000000000000110111000000000000000000000000001000110000000000000000000000000000111100000000000000000000000000000000 /
b11100001 (
b11100001 ,
1#
#226000
b11100010 (
b11100010 ,
#227000
b11100011 (
b11100011 ,
#228000
b11100100 (
b11100100 ,
#229000
b11100101 (
b11100101 ,
#230000
b11100110 (
b11100110 ,
0#
#231000
b11100111 (
b11100111 ,
#232000
b11101000 (
b11101000 ,
#233000
b11101001 (
b11101001 ,
#234000
b11101010 (
b11101010 ,
#235000
bx00000000000000000000000011101011000000000000000000000000110101110000000000000000000000001100001100000000000000000000000010101111000000000000000000000000100110110000000000000000000000001000011100000000000000000000000001110011000000000000000000000000010111110000000000000000000000000100101100000000000000000000000000110111000000000000000000000000001000110000000000000000000000000000111100000000000000000000000000000000 /
b11101011 (
b11101011 ,
1#
#236000
b11101100 (
b11101100 ,
#237000
b11101101 (
b11101101 ,
#238000
b11101110 (
b11101110 ,
#239000
b11101111 (
b11101111 ,
#240000
b11110000 (
b11110000 ,
0#
b1101 '
b1101 +
#241000
b11110001 (
b11110001 ,
#242000
b11110010 (
b11110010 ,
#243000
b11110011 (
b11110011 ,
#244000
b11110100 (
b11110100 ,
#245000
bx0000000000000000000000001111010100000000000000000000000011101011000000000000000000000000110101110000000000000000000000001100001100000000000000000000000010101111000000000000000000000000100110110000000000000000000000001000011100000000000000000000000001110011000000000000000000000000010111110000000000000000000000000100101100000000000000000000000000110111000000000000000000000000001000110000000000000000000000000000111100000000000000000000000000000000 /
b11110101 (
b11110101 ,
1#
#246000
b11110110 (
b11110110 ,
#247000
b11110111 (
b11110111 ,
#248000
b11111000 (
b11111000 ,
#249000
b11111001 (
b11111001 ,
#250000
b11111010 (
b11111010 ,
0#
#251000
b11111011 (
b11111011 ,
#252000
b11111100 (
b11111100 ,
#253000
b11111101 (
b11111101 ,
#254000
b11111110 (
b11111110 ,
#255000
bx0000000000000000000000001111111100000000000000000000000011101011000000000000000000000000110101110000000000000000000000001100001100000000000000000000000010101111000000000000000000000000100110110000000000000000000000001000011100000000000000000000000001110011000000000000000000000000010111110000000000000000000000000100101100000000000000000000000000110111000000000000000000000000001000110000000000000000000000000000111100000000000000000000000000000000 /
b11111111 (
b11111111 ,
1#
#256000
b100000000 (
b100000000 ,
#257000
b100000001 (
b100000001 ,
#258000
b100000010 (
b100000010 ,
#259000
b100000011 (
b100000011 ,
#260000
b100000100 (
b100000100 ,
0#
b1110 '
b1110 +
#261000
b100000101 (
b100000101 ,
#262000
b100000110 (
b100000110 ,
#263000
b100000111 (
b100000111 ,
#264000
b100001000 (
b100001000 ,
#265000
bx000000000000000000000001000010010000000000000000000000001111111100000000000000000000000011101011000000000000000000000000110101110000000000000000000000001100001100000000000000000000000010101111000000000000000000000000100110110000000000000000000000001000011100000000000000000000000001110011000000000000000000000000010111110000000000000000000000000100101100000000000000000000000000110111000000000000000000000000001000110000000000000000000000000000111100000000000000000000000000000000 /
b100001001 (
b100001001 ,
1#
#266000
b100001010 (
b100001010 ,
#267000
b100001011 (
b100001011 ,
#268000
b100001100 (
b100001100 ,
#269000
b100001101 (
b100001101 ,
#270000
b100001110 (
b100001110 ,
0#
#271000
b100001111 (
b100001111 ,
#272000
b100010000 (
b100010000 ,
#273000
b100010001 (
b100010001 ,
#274000
b100010010 (
b100010010 ,
#275000
bx000000000000000000000001000100110000000000000000000000001111111100000000000000000000000011101011000000000000000000000000110101110000000000000000000000001100001100000000000000000000000010101111000000000000000000000000100110110000000000000000000000001000011100000000000000000000000001110011000000000000000000000000010111110000000000000000000000000100101100000000000000000000000000110111000000000000000000000000001000110000000000000000000000000000111100000000000000000000000000000000 /
b100010011 (
b100010011 ,
1#
#276000
b100010100 (
b100010100 ,
#277000
b100010101 (
b100010101 ,
#278000
b100010110 (
b100010110 ,
#279000
b100010111 (
b100010111 ,
#280000
b100011000 (
b100011000 ,
0#
b1111 '
b1111 +
#281000
b100011001 (
b100011001 ,
#282000
b100011010 (
b100011010 ,
#283000
b100011011 (
b100011011 ,
#284000
b100011100 (
b100011100 ,
#285000
bx00000000000000000000000100011101000000000000000000000001000100110000000000000000000000001111111100000000000000000000000011101011000000000000000000000000110101110000000000000000000000001100001100000000000000000000000010101111000000000000000000000000100110110000000000000000000000001000011100000000000000000000000001110011000000000000000000000000010111110000000000000000000000000100101100000000000000000000000000110111000000000000000000000000001000110000000000000000000000000000111100000000000000000000000000000000 /
b100011101 (
b100011101 ,
1#
#286000
b100011110 (
b100011110 ,
#287000
b100011111 (
b100011111 ,
#288000
b100100000 (
b100100000 ,
#289000
b100100001 (
b100100001 ,
#290000
b100100010 (
b100100010 ,
0#
#291000
b100100011 (
b100100011 ,
#292000
b100100100 (
b100100100 ,
#293000
b100100101 (
b100100101 ,
#294000
b100100110 (
b100100110 ,
#295000
bx00000000000000000000000100100111000000000000000000000001000100110000000000000000000000001111111100000000000000000000000011101011000000000000000000000000110101110000000000000000000000001100001100000000000000000000000010101111000000000000000000000000100110110000000000000000000000001000011100000000000000000000000001110011000000000000000000000000010111110000000000000000000000000100101100000000000000000000000000110111000000000000000000000000001000110000000000000000000000000000111100000000000000000000000000000000 /
b100100111 (
b100100111 ,
1#
#296000
b100101000 (
b100101000 ,
#297000
b100101001 (
b100101001 ,
#298000
b100101010 (
b100101010 ,
#299000
b100101011 (
b100101011 ,
#300000
b100101100 (
b100101100 ,
0#
b10000 '
b10000 +
#301000
b100101101 (
b100101101 ,
#302000
b100101110 (
b100101110 ,
#303000
b100101111 (
b100101111 ,
#304000
b100110000 (
b100110000 ,
#305000
bx0000000000000000000000010011000100000000000000000000000100100111000000000000000000000001000100110000000000000000000000001111111100000000000000000000000011101011000000000000000000000000110101110000000000000000000000001100001100000000000000000000000010101111000000000000000000000000100110110000000000000000000000001000011100000000000000000000000001110011000000000000000000000000010111110000000000000000000000000100101100000000000000000000000000110111000000000000000000000000001000110000000000000000000000000000111100000000000000000000000000000000 /
b100110001 (
b100110001 ,
1#
#306000
b100110010 (
b100110010 ,
#307000
b100110011 (
b100110011 ,
#308000
b100110100 (
b100110100 ,
#309000
b100110101 (
b100110101 ,
#310000
b100110110 (
b100110110 ,
0#
#311000
b100110111 (
b100110111 ,
#312000
b100111000 (
b100111000 ,
#313000
b100111001 (
b100111001 ,
#314000
b100111010 (
b100111010 ,
#315000
bx0000000000000000000000010011101100000000000000000000000100100111000000000000000000000001000100110000000000000000000000001111111100000000000000000000000011101011000000000000000000000000110101110000000000000000000000001100001100000000000000000000000010101111000000000000000000000000100110110000000000000000000000001000011100000000000000000000000001110011000000000000000000000000010111110000000000000000000000000100101100000000000000000000000000110111000000000000000000000000001000110000000000000000000000000000111100000000000000000000000000000000 /
b100111011 (
b100111011 ,
1#
#316000
b100111100 (
b100111100 ,
#317000
b100111101 (
b100111101 ,
#318000
b100111110 (
b100111110 ,
#319000
b100111111 (
b100111111 ,
#320000
b101000000 (
b101000000 ,
0#
b10001 '
b10001 +
#321000
b101000001 (
b101000001 ,
#322000
b101000010 (
b101000010 ,
#323000
b101000011 (
b101000011 ,
#324000
b101000100 (
b101000100 ,
#325000
bx000000000000000000000001010001010000000000000000000000010011101100000000000000000000000100100111000000000000000000000001000100110000000000000000000000001111111100000000000000000000000011101011000000000000000000000000110101110000000000000000000000001100001100000000000000000000000010101111000000000000000000000000100110110000000000000000000000001000011100000000000000000000000001110011000000000000000000000000010111110000000000000000000000000100101100000000000000000000000000110111000000000000000000000000001000110000000000000000000000000000111100000000000000000000000000000000 /
b101000101 (
b101000101 ,
1#
#326000
b101000110 (
b101000110 ,
#327000
b101000111 (
b101000111 ,
#328000
b101001000 (
b101001000 ,
#329000
b101001001 (
b101001001 ,
#330000
b101001010 (
b101001010 ,
0#
#331000
b101001011 (
b101001011 ,
#332000
b101001100 (
b101001100 ,
#333000
b101001101 (
b101001101 ,
#334000
b101001110 (
b101001110 ,
#335000
bx000000000000000000000001010011110000000000000000000000010011101100000000000000000000000100100111000000000000000000000001000100110000000000000000000000001111111100000000000000000000000011101011000000000000000000000000110101110000000000000000000000001100001100000000000000000000000010101111000000000000000000000000100110110000000000000000000000001000011100000000000000000000000001110011000000000000000000000000010111110000000000000000000000000100101100000000000000000000000000110111000000000000000000000000001000110000000000000000000000000000111100000000000000000000000000000000 /
b101001111 (
b101001111 ,
1#
#336000
b101010000 (
b101010000 ,
#337000
b101010001 (
b101010001 ,
#338000
b101010010 (
b101010010 ,
#339000
b101010011 (
b101010011 ,
#340000
b101010100 (
b101010100 ,
0#
b10010 '
b10010 +
#341000
b101010101 (
b101010101 ,
#342000
b101010110 (
b101010110 ,
#343000
b101010111 (
b101010111 ,
#344000
b101011000 (
b101011000 ,
#345000
bx00000000000000000000000101011001000000000000000000000001010011110000000000000000000000010011101100000000000000000000000100100111000000000000000000000001000100110000000000000000000000001111111100000000000000000000000011101011000000000000000000000000110101110000000000000000000000001100001100000000000000000000000010101111000000000000000000000000100110110000000000000000000000001000011100000000000000000000000001110011000000000000000000000000010111110000000000000000000000000100101100000000000000000000000000110111000000000000000000000000001000110000000000000000000000000000111100000000000000000000000000000000 /
b101011001 (
b101011001 ,
1#
#346000
b101011010 (
b101011010 ,
#347000
b101011011 (
b101011011 ,
#348000
b101011100 (
b101011100 ,
#349000
b101011101 (
b101011101 ,
#350000
b101011110 (
b101011110 ,
0#
#351000
b101011111 (
b101011111 ,
#352000
b101100000 (
b101100000 ,
#353000
b101100001 (
b101100001 ,
#354000
b101100010 (
b101100010 ,
#355000
bx00000000000000000000000101100011000000000000000000000001010011110000000000000000000000010011101100000000000000000000000100100111000000000000000000000001000100110000000000000000000000001111111100000000000000000000000011101011000000000000000000000000110101110000000000000000000000001100001100000000000000000000000010101111000000000000000000000000100110110000000000000000000000001000011100000000000000000000000001110011000000000000000000000000010111110000000000000000000000000100101100000000000000000000000000110111000000000000000000000000001000110000000000000000000000000000111100000000000000000000000000000000 /
b101100011 (
b101100011 ,
1#
#356000
b101100100 (
b101100100 ,
#357000
b101100101 (
b101100101 ,
#358000
b101100110 (
b101100110 ,
#359000
b101100111 (
b101100111 ,
#360000
b101101000 (
b101101000 ,
0#
b10011 '
b10011 +
#361000
b101101001 (
b101101001 ,
#362000
b101101010 (
b101101010 ,
#363000
b101101011 (
b101101011 ,
#364000
b101101100 (
b101101100 ,
#365000
bx0000000000000000000000010110110100000000000000000000000101100011000000000000000000000001010011110000000000000000000000010011101100000000000000000000000100100111000000000000000000000001000100110000000000000000000000001111111100000000000000000000000011101011000000000000000000000000110101110000000000000000000000001100001100000000000000000000000010101111000000000000000000000000100110110000000000000000000000001000011100000000000000000000000001110011000000000000000000000000010111110000000000000000000000000100101100000000000000000000000000110111000000000000000000000000001000110000000000000000000000000000111100000000000000000000000000000000 /
b101101101 (
b101101101 ,
1#
#366000
b101101110 (
b101101110 ,
#367000
b101101111 (
b101101111 ,
#368000
b101110000 (
b101110000 ,
#369000
b101110001 (
b101110001 ,
#370000
b101110010 (
b101110010 ,
0#
#371000
b101110011 (
b101110011 ,
#372000
b101110100 (
b101110100 ,
#373000
b101110101 (
b101110101 ,
#374000
b101110110 (
b101110110 ,
#375000
bx0000000000000000000000010111011100000000000000000000000101100011000000000000000000000001010011110000000000000000000000010011101100000000000000000000000100100111000000000000000000000001000100110000000000000000000000001111111100000000000000000000000011101011000000000000000000000000110101110000000000000000000000001100001100000000000000000000000010101111000000000000000000000000100110110000000000000000000000001000011100000000000000000000000001110011000000000000000000000000010111110000000000000000000000000100101100000000000000000000000000110111000000000000000000000000001000110000000000000000000000000000111100000000000000000000000000000000 /
b101110111 (
b101110111 ,
1#
#376000
b101111000 (
b101111000 ,
#377000
b101111001 (
b101111001 ,
#378000
b101111010 (
b101111010 ,
#379000
b101111011 (
b101111011 ,
#380000
b101111100 (
b101111100 ,
0#
b10100 '
b10100 +
#381000
b101111101 (
b101111101 ,
#382000
b101111110 (
b101111110 ,
#383000
b101111111 (
b101111111 ,
#384000
b110000000 (
b110000000 ,
#385000
bx000000000000000000000001100000010000000000000000000000010111011100000000000000000000000101100011000000000000000000000001010011110000000000000000000000010011101100000000000000000000000100100111000000000000000000000001000100110000000000000000000000001111111100000000000000000000000011101011000000000000000000000000110101110000000000000000000000001100001100000000000000000000000010101111000000000000000000000000100110110000000000000000000000001000011100000000000000000000000001110011000000000000000000000000010111110000000000000000000000000100101100000000000000000000000000110111000000000000000000000000001000110000000000000000000000000000111100000000000000000000000000000000 /
b110000001 (
b110000001 ,
1#
#386000
b110000010 (
b110000010 ,
#387000
b110000011 (
b110000011 ,
#388000
b110000100 (
b110000100 ,
#389000
b110000101 (
b110000101 ,
#390000
b110000110 (
b110000110 ,
0#
#391000
b110000111 (
b110000111 ,
#392000
b110001000 (
b110001000 ,
#393000
b110001001 (
b110001001 ,
#394000
b110001010 (
b110001010 ,
#395000
bx000000000000000000000001100010110000000000000000000000010111011100000000000000000000000101100011000000000000000000000001010011110000000000000000000000010011101100000000000000000000000100100111000000000000000000000001000100110000000000000000000000001111111100000000000000000000000011101011000000000000000000000000110101110000000000000000000000001100001100000000000000000000000010101111000000000000000000000000100110110000000000000000000000001000011100000000000000000000000001110011000000000000000000000000010111110000000000000000000000000100101100000000000000000000000000110111000000000000000000000000001000110000000000000000000000000000111100000000000000000000000000000000 /
b110001011 (
b110001011 ,
1#
#396000
b110001100 (
b110001100 ,
#397000
b110001101 (
b110001101 ,
#398000
b110001110 (
b110001110 ,
#399000
b110001111 (
b110001111 ,
#400000
b110010000 (
b110010000 ,
0#
b10101 '
b10101 +
#401000
b110010001 (
b110010001 ,
#402000
b110010010 (
b110010010 ,
#403000
b110010011 (
b110010011 ,
#404000
b110010100 (
b110010100 ,
#405000
bx00000000000000000000000110010101000000000000000000000001100010110000000000000000000000010111011100000000000000000000000101100011000000000000000000000001010011110000000000000000000000010011101100000000000000000000000100100111000000000000000000000001000100110000000000000000000000001111111100000000000000000000000011101011000000000000000000000000110101110000000000000000000000001100001100000000000000000000000010101111000000000000000000000000100110110000000000000000000000001000011100000000000000000000000001110011000000000000000000000000010111110000000000000000000000000100101100000000000000000000000000110111000000000000000000000000001000110000000000000000000000000000111100000000000000000000000000000000 /
b110010101 (
b110010101 ,
1#
#406000
b110010110 (
b110010110 ,
#407000
b110010111 (
b110010111 ,
#408000
b110011000 (
b110011000 ,
#409000
b110011001 (
b110011001 ,
#410000
b110011010 (
b110011010 ,
0#
#411000
b110011011 (
b110011011 ,
#412000
b110011100 (
b110011100 ,
#413000
b110011101 (
b110011101 ,
#414000
b110011110 (
b110011110 ,
