I2C_controller/I2C_Slave/i2c_slave.v
    /*
I2C Slave

Input:
    clk:            FPGA Base Clock (50MHz)
    SCL:            Serial Clock
    SDA:            Serial DATA
    slave_addr:     Slave Address
    rst:            Async Reset

Output:
    debug:          Debug Port for internal Signals
*/



module i2c_slave(
    input clk,
    input SCL,
    inout SDA,
    input[6:0] slave_addr,
    input rst,                       // Async Active High Reset
	 output[5:0] debug
);  

    // I2C State Def
    reg[38:0] i2c_state; wire[38:0] i2c_next_state		/* synthesis preserve */;
    parameter INIT=8'd0,ADDR6=8'd1,ADDR5=8'd2,ADDR4=8'd3,ADDR3=8'd4,ADDR2=8'd5,ADDR1=8'd6,ADDR0=8'd7,RW_t=8'd8,ACK1=8'd9,WAIT=8'd10,REG_ADDR7=8'd11,REG_ADDR6=8'd12,REG_ADDR5=8'd13,REG_ADDR4=8'd14,REG_ADDR3=8'd15,REG_ADDR2=8'd16,REG_ADDR1=8'd17,REG_ADDR0=8'd18,ACK2=8'd19,DATA7=8'd20,DATA6=8'd21,DATA5=8'd22,DATA4=8'd23,DATA3=8'd24,DATA2=8'd25,DATA1=8'd26,DATA0=8'd27,ACK3=8'd28,ACK4=8'd29,DATA_OUT7=8'd30,DATA_OUT6=8'd31,DATA_OUT5=8'd32,DATA_OUT4=8'd33,DATA_OUT3=8'd34,DATA_OUT2=8'd35,DATA_OUT1=8'd36,DATA_OUT0=8'd37,NACK=8'd38;
	 
    // DATA IO Def
    reg[7:0] data_memory [7:0]	    /* synthesis preserve */;
    reg[7:0] addr_reg				/* synthesis preserve */;
    wire acquire_data_address		/* synthesis preserve */;

    // I2C Data Register
    reg[7:0] data_reg;
    always@(posedge SCL or posedge rst) data_reg <= (rst) ? 8'd0 : {data_reg[6:0],SDA};

    // Output Register Loading
    reg[7:0] output_reg;
    always@(posedge i2c_state[ACK4]) output_reg <= data_memory[addr_reg];                               // When in ACK4 stage, load output register accordingly

    assign acquire_data_address = (i2c_state[ACK2])|(i2c_state[DATA7])|(i2c_state[NACK]) ? 1'b1 : 1'b0;
    always@(posedge acquire_data_address or posedge rst) begin
        if(rst) addr_reg <= 8'd0;
        else addr_reg <= (i2c_state[ACK2]) ? data_reg : (i2c_state[DATA7])|(i2c_state[NACK]) ? addr_reg+7'h1 : addr_reg;        // For multibyte address increment
    end
    always@(posedge i2c_state[ACK3]) data_memory[addr_reg] <= data_reg;

    // SDA Output / ACK Handling
    reg SDA_input; 
    always@(posedge SCL) SDA_input <= SDA;
    wire SDA_control, ACK_control, Data_control;
	assign SDA_control = ACK_control | Data_control;                                                    // Pull SDA to LOW when in ACK or DATA output
    assign ACK_control = (i2c_state[ACK1])|(i2c_state[ACK2])|(i2c_state[ACK3])|(i2c_state[ACK4]);
    assign Data_control = (i2c_state[DATA_OUT7]&~output_reg[7])|(i2c_state[DATA_OUT6]&~output_reg[6])|(i2c_state[DATA_OUT5]&~output_reg[5])|(i2c_state[DATA_OUT4]&~output_reg[4])|(i2c_state[DATA_OUT3]&~output_reg[3])|(i2c_state[DATA_OUT2]&~output_reg[2])|(i2c_state[DATA_OUT1]&~output_reg[1])|(i2c_state[DATA_OUT0]&~output_reg[0]);
    assign SDA = SDA_control ? 1'b0 : 1'bz;

    // Generation of START/STOP/Data Valid Signal
    reg prev_val, curr_val;                             // 2 Bits Shift Register to constantly scaning for SDA changes
    always@(posedge clk) curr_val <= SDA;
	always@(posedge clk) prev_val <= curr_val;
    
    wire start_sign, stop_sign;                         // Note: SDA has to be stablized 2 clock cycle before SCL rising edges to avoid incorrect trigger of START/STOP signal
    assign start_sign = prev_val & ~curr_val & SCL;     // When SCL is high, previous value = 1 but current value is 0, indicating a START signal
    assign stop_sign = ~prev_val & curr_val & SCL;      // When SCL is high, previous value = 0 but current value is 1, indicating a STOP signal


    /*
    When STOP Signal issued for bus idle, SCL will not have falling edge. Hence reset need to be able to detect new START signal 

        STOP Signal Issued       START Signal Issued
               ________________________
    SCL ______/                        \______
                       ____________
    SDA ______________/            \______________________
    */
    reg start_received, stop_received;
    always@(posedge SCL or posedge start_sign) start_received <= start_sign ? 1'b1: 1'b0;                                               // Use Trigger Latch to hold Start Signal until next rising edge of SCL
    always@(posedge SCL or posedge stop_sign or posedge start_sign) stop_received <= start_sign ? 1'b0 : stop_sign ? 1'b1: 1'b0;        // Use Trigger Latch to hold Stop Signal until next rising edge of SCL or new Start signal.
    	
    // I2C FSM
    always@(negedge (SCL) or posedge rst or posedge stop_received) begin
        if(rst) i2c_state <= 39'd1;
		else if(stop_received) i2c_state <= 39'd1;
        else i2c_state <= i2c_next_state;
    end

    assign i2c_next_state[INIT]         = i2c_state[INIT] & ~start_received;
    assign i2c_next_state[ADDR6]        = (i2c_state[INIT] & start_received) | (i2c_state[DATA7] & start_received);
    assign i2c_next_state[ADDR5]        = i2c_state[ADDR6];
    assign i2c_next_state[ADDR4]        = i2c_state[ADDR5];
    assign i2c_next_state[ADDR3]        = i2c_state[ADDR4];
    assign i2c_next_state[ADDR2]        = i2c_state[ADDR3];
    assign i2c_next_state[ADDR1]        = i2c_state[ADDR2];
    assign i2c_next_state[ADDR0]        = i2c_state[ADDR1];
    assign i2c_next_state[RW_t]         = i2c_state[ADDR0];
    assign i2c_next_state[ACK1]         = i2c_state[RW_t] & (data_reg[7:1] == slave_addr) & (SDA_input==1'b0);
    assign i2c_next_state[WAIT]         = (i2c_state[RW_t] & (data_reg[7:1] != slave_addr)) | (i2c_state[NACK] & (SDA_input==1'b0));
    assign i2c_next_state[ACK4]         = i2c_state[RW_t] & (data_reg[7:1] == slave_addr) & (SDA_input==1'b1);
    assign i2c_next_state[REG_ADDR7]    = i2c_state[ACK1];
    assign i2c_next_state[REG_ADDR6]    = i2c_state[REG_ADDR7];
    assign i2c_next_state[REG_ADDR5]    = i2c_state[REG_ADDR6];
    assign i2c_next_state[REG_ADDR4]    = i2c_state[REG_ADDR5];
    assign i2c_next_state[REG_ADDR3]    = i2c_state[REG_ADDR4];
    assign i2c_next_state[REG_ADDR2]    = i2c_state[REG_ADDR3];
    assign i2c_next_state[REG_ADDR1]    = i2c_state[REG_ADDR2];
    assign i2c_next_state[REG_ADDR0]    = i2c_state[REG_ADDR1];
    assign i2c_next_state[ACK2]         = i2c_state[REG_ADDR0];
    assign i2c_next_state[DATA7]        = i2c_state[ACK2];
    assign i2c_next_state[DATA6]        = i2c_state[DATA7] & (~start_received & ~stop_received);
    assign i2c_next_state[DATA5]        = i2c_state[DATA6];
    assign i2c_next_state[DATA4]        = i2c_state[DATA5];
    assign i2c_next_state[DATA3]        = i2c_state[DATA4];
    assign i2c_next_state[DATA2]        = i2c_state[DATA3];
    assign i2c_next_state[DATA1]        = i2c_state[DATA2];
    assign i2c_next_state[DATA0]        = i2c_state[DATA1];
    assign i2c_next_state[ACK3]         = i2c_state[DATA0];
    assign i2c_next_state[DATA_OUT7]    = i2c_state[ACK4] | (i2c_state[NACK] & (SDA_input == 1'b1));
    assign i2c_next_state[DATA_OUT6]    = i2c_state[DATA_OUT7];
    assign i2c_next_state[DATA_OUT5]    = i2c_state[DATA_OUT6];
    assign i2c_next_state[DATA_OUT4]    = i2c_state[DATA_OUT5];
    assign i2c_next_state[DATA_OUT3]    = i2c_state[DATA_OUT4];
    assign i2c_next_state[DATA_OUT2]    = i2c_state[DATA_OUT3];
    assign i2c_next_state[DATA_OUT1]    = i2c_state[DATA_OUT2];
    assign i2c_next_state[DATA_OUT0]    = i2c_state[DATA_OUT1];
    assign i2c_next_state[NACK]         = i2c_state[DATA_OUT0];

endmodule

I2C_controller/I2C_Master/i2c_master.v
    /*
I2C Master

Input:
    SCL:            Serial Clock
    SDA:            Serial DATA
    slave_addr:     Slave Address
    slave_reg_addr: Slave Register Address
    start_tx:       Start Transmission Signal
    operation:      read = 0, write = 1
    rst:            Async Reset
*/

module i2c_master(
    input clk,
    output SCL,
    inout SDA,
    input[6:0] slave_addr,
    input [7:0] slave_reg_addr,
    input [7:0] data_i,
    input start_tx,
    input operation,
    output [7:0] data_o,
    input rst                       // Async Reset
);

// SCL Generation   --> 100KHz Speed
// Default FPGA Clock = 50MHz --> 50M/100K = 500
reg SCL_clk;
assign SCL = SCL_clk;
reg[8:0] clk_counter;

// I2C Master FSM
reg[7:0] i2c_master_state, i2c_master_next_state;
parameter INIT=8'd0,START=8'd1,ADDR6=8'd2,ADDR5=8'd3,ADDR4=8'd4,ADDR3=8'd5,ADDR2=8'd6,ADDR1=8'd7,ADDR0=8'd8;
parameter RW=8'd9,ACK1=8'd10,STOP=8'd11,REG7=8'd12,ACK2=8'd20,DATA7=8'd21,ACK3=8'd29;

reg BusBusy;
always@(posedge (i2c_master_state == INIT)) BusBusy = start_tx ? 1'b0 : 1'b1;

always@(posedge clk or posedge rst) begin
    if(rst) begin 
        clk_counter <= 9'b0; 
        SCL_clk <= 1'b1;
    end
    else begin
        if(BusBusy) begin
            clk_counter <= (clk_counter == 9'd500) ? 9'd0 : clk_counter+1'b1;
            SCL_clk <= (clk_counter == 9'd500) ? ~SCL_clk : SCL_clk;
        end else begin
            clk_counter <= 9'b0; 
            SCL_clk <= 1'b1;
        end
    end
end

// SDA IO Control
reg SDA_i, SDA_value;
always@(posedge SCL) SDA_i <= SDA;
wire SDA_control, ACK_control, Data_control, Start_control, Stop_control;
assign SDA_control = ACK_control | Data_control | Start_control | Stop_control;
assign ACK_control = ~((i2c_master_state == ACK1) | (i2c_master_state == ACK2) | (i2c_master_state == ACK3));   // When in ACK Stage, Let Slave take Control
assign Data_control = ~SDA_value;
assign SDA = SDA_control ? 1'b0 : 1'bz;

reg [3:0] SDA_delay;
always@(posedge clk or posedge rst) SDA_delay <= ((i2c_master_state == START)|(i2c_master_state == STOP)&(SCL)) ? ((SDA_delay > 4'h0) ? SDA_delay - 1'b1 : SDA_delay) : 4'hF;
assign Start_control = (i2c_master_state == START) & (SDA_delay == 4'd0);
assign Stop_control = (i2c_master_state == STOP) & (SDA_delay != 4'd0);

wire rw;
assign rw = operation;

always@(*) begin
    case(i2c_master_state)
        START:      SDA_value = (SCL & (SDA_delay == 4'h0)) ? 1'b0 : 1'b1;
        ADDR6:      SDA_value = slave_addr[6];
        ADDR5:      SDA_value = slave_addr[5];
        ADDR4:      SDA_value = slave_addr[4];
        ADDR3:      SDA_value = slave_addr[3];
        ADDR2:      SDA_value = slave_addr[2];
        ADDR1:      SDA_value = slave_addr[1];
        ADDR0:      SDA_value = slave_addr[0];
        RW:         SDA_value = rw;
        default:    SDA_value = 1'b1;
    endcase
end


always@(negedge SCL or posedge rst or posedge start_tx) begin
    if(rst) i2c_master_state <= INIT;
    else if(start_tx) i2c_master_state <= START;
    else i2c_master_state <= i2c_master_next_state;
end

always@(*) begin
    case(i2c_master_state)
        INIT:       i2c_master_next_state = start_tx ? START : INIT;
        START:      i2c_master_next_state = ADDR6;
        STOP:       i2c_master_next_state = INIT;
        ACK1:       i2c_master_next_state = SDA_i ? STOP : REG7;
        ACK2:       i2c_master_next_state = SDA_i ? STOP : DATA7;
        ACK3:       i2c_master_next_state = STOP;
        default :   i2c_master_next_state = i2c_master_state + 1'd1;
    endcase
end
endmodule

I2C_controller/I2C_Master/i2c_tb_master.v
`timescale 1ns/1ns

//`include "../I2C_Salve/i2c_slave.v"
//`include "i2c_master.v"

module master_tb_top();

    wire SCL,SDA;
    reg clk,start_tx,rst;

    always #10 clk <= ~clk;  // 50MHz Clock --> 20ns
    initial begin
        $dumpfile("tb_wave.vcd");
        $dumpvars(0, master_tb_top);
        clk = 1'b0; rst = 1'b1; start_tx = 1'b0; #10; 
        rst = 1'b0; #13;
        
        start_tx = 1'b1; # 100; start_tx = 1'b0;
        #500000;
        $finish;
    end

    wire[7:0] data_o;
    i2c_master master(  clk,SCL,SDA,7'h11,8'h00, 8'hAA, start_tx, 1'b0, data_o, rst);
    i2c_slave slave0(   clk,SCL,SDA,7'h11,rst);

endmodule

I2C_controller/I2C_Master/tb_wave.vcd
$date
	Thu Dec 21 09:47:44 2023
$end
$version
	ModelSim Version 10.5b
$end
$timescale
	1ns
$end

$scope module master_tb_top $end
$var wire 1 ! SCL $end
$var wire 1 " SDA $end
$var reg 1 # clk $end
$var reg 1 $ start_tx $end
$var reg 1 % rst $end
$var wire 1 & data_o [7] $end
$var wire 1 ' data_o [6] $end
$var wire 1 ( data_o [5] $end
$var wire 1 ) data_o [4] $end
$var wire 1 * data_o [3] $end
$var wire 1 + data_o [2] $end
$var wire 1 , data_o [1] $end
$var wire 1 - data_o [0] $end

$scope module master $end
$var parameter 8 . INIT $end
$var parameter 8 / START $end
$var parameter 8 0 ADDR6 $end
$var parameter 8 1 ADDR5 $end
$var parameter 8 2 ADDR4 $end
$var parameter 8 3 ADDR3 $end
$var parameter 8 4 ADDR2 $end
$var parameter 8 5 ADDR1 $end
$var parameter 8 6 ADDR0 $end
$var parameter 8 7 RW $end
$var parameter 8 8 ACK1 $end
$var parameter 8 9 STOP $end
$var parameter 8 : REG7 $end
$var parameter 8 ; ACK2 $end
$var parameter 8 < DATA7 $end
$var parameter 8 = ACK3 $end
$var wire 1 > clk $end
$var wire 1 ! SCL $end
$var wire 1 " SDA $end
$var wire 1 ? slave_addr [6] $end
$var wire 1 @ slave_addr [5] $end
$var wire 1 A slave_addr [4] $end
$var wire 1 B slave_addr [3] $end
$var wire 1 C slave_addr [2] $end
$var wire 1 D slave_addr [1] $end
$var wire 1 E slave_addr [0] $end
$var wire 1 F slave_reg_addr [7] $end
$var wire 1 G slave_reg_addr [6] $end
$var wire 1 H slave_reg_addr [5] $end
$var wire 1 I slave_reg_addr [4] $end
$var wire 1 J slave_reg_addr [3] $end
$var wire 1 K slave_reg_addr [2] $end
$var wire 1 L slave_reg_addr [1] $end
$var wire 1 M slave_reg_addr [0] $end
$var wire 1 N data_i [7] $end
$var wire 1 O data_i [6] $end
$var wire 1 P data_i [5] $end
$var wire 1 Q data_i [4] $end
$var wire 1 R data_i [3] $end
$var wire 1 S data_i [2] $end
$var wire 1 T data_i [1] $end
$var wire 1 U data_i [0] $end
$var wire 1 V start_tx $end
$var wire 1 W operation $end
$var wire 1 & data_o [7] $end
$var wire 1 ' data_o [6] $end
$var wire 1 ( data_o [5] $end
$var wire 1 ) data_o [4] $end
$var wire 1 * data_o [3] $end
$var wire 1 + data_o [2] $end
$var wire 1 , data_o [1] $end
$var wire 1 - data_o [0] $end
$var wire 1 X rst $end
$var reg 1 Y SCL_clk $end
$var reg 9 Z clk_counter [8:0] $end
$var reg 8 [ i2c_master_state [7:0] $end
$var reg 8 \ i2c_master_next_state [7:0] $end
$var reg 1 ] BusBusy $end
$var reg 1 ^ SDA_i $end
$var reg 1 _ SDA_value $end
$var wire 1 ` SDA_control $end
$var wire 1 a ACK_control $end
$var wire 1 b Data_control $end
$var wire 1 c Start_control $end
$var wire 1 d Stop_control $end
$var reg 4 e SDA_delay [3:0] $end
$var wire 1 f rw $end
$upscope $end

$scope module slave0 $end
$var parameter 8 g INIT $end
$var parameter 8 h ADDR6 $end
$var parameter 8 i ADDR5 $end
$var parameter 8 j ADDR4 $end
$var parameter 8 k ADDR3 $end
$var parameter 8 l ADDR2 $end
$var parameter 8 m ADDR1 $end
$var parameter 8 n ADDR0 $end
$var parameter 8 o RW_t $end
$var parameter 8 p ACK1 $end
$var parameter 8 q WAIT $end
$var parameter 8 r REG_ADDR7 $end
$var parameter 8 s REG_ADDR6 $end
$var parameter 8 t REG_ADDR5 $end
$var parameter 8 u REG_ADDR4 $end
$var parameter 8 v REG_ADDR3 $end
$var parameter 8 w REG_ADDR2 $end
$var parameter 8 x REG_ADDR1 $end
$var parameter 8 y REG_ADDR0 $end
$var parameter 8 z ACK2 $end
$var parameter 8 { DATA7 $end
$var parameter 8 | DATA6 $end
$var parameter 8 } DATA5 $end
$var parameter 8 ~ DATA4 $end
$var parameter 8 !! DATA3 $end
$var parameter 8 "! DATA2 $end
$var parameter 8 #! DATA1 $end
$var parameter 8 $! DATA0 $end
$var parameter 8 %! ACK3 $end
$var parameter 8 &! ACK4 $end
$var parameter 8 '! DATA_OUT7 $end
$var parameter 8 (! DATA_OUT6 $end
$var parameter 8 )! DATA_OUT5 $end
$var parameter 8 *! DATA_OUT4 $end
$var parameter 8 +! DATA_OUT3 $end
$var parameter 8 ,! DATA_OUT2 $end
$var parameter 8 -! DATA_OUT1 $end
$var parameter 8 .! DATA_OUT0 $end
$var parameter 8 /! NACK $end
$var wire 1 0! clk $end
$var wire 1 ! SCL $end
$var wire 1 " SDA $end
$var wire 1 1! slave_addr [6] $end
$var wire 1 2! slave_addr [5] $end
$var wire 1 3! slave_addr [4] $end
$var wire 1 4! slave_addr [3] $end
$var wire 1 5! slave_addr [2] $end
$var wire 1 6! slave_addr [1] $end
$var wire 1 7! slave_addr [0] $end
$var wire 1 8! rst $end
$var wire 1 9! debug [5] $end
$var wire 1 :! debug [4] $end
$var wire 1 ;! debug [3] $end
$var wire 1 <! debug [2] $end
$var wire 1 =! debug [1] $end
$var wire 1 >! debug [0] $end
$var reg 39 ?! i2c_state [38:0] $end
$var wire 1 @! i2c_next_state [38] $end
$var wire 1 A! i2c_next_state [37] $end
$var wire 1 B! i2c_next_state [36] $end
$var wire 1 C! i2c_next_state [35] $end
$var wire 1 D! i2c_next_state [34] $end
$var wire 1 E! i2c_next_state [33] $end
$var wire 1 F! i2c_next_state [32] $end
$var wire 1 G! i2c_next_state [31] $end
$var wire 1 H! i2c_next_state [30] $end
$var wire 1 I! i2c_next_state [29] $end
$var wire 1 J! i2c_next_state [28] $end
$var wire 1 K! i2c_next_state [27] $end
$var wire 1 L! i2c_next_state [26] $end
$var wire 1 M! i2c_next_state [25] $end
$var wire 1 N! i2c_next_state [24] $end
$var wire 1 O! i2c_next_state [23] $end
$var wire 1 P! i2c_next_state [22] $end
$var wire 1 Q! i2c_next_state [21] $end
$var wire 1 R! i2c_next_state [20] $end
$var wire 1 S! i2c_next_state [19] $end
$var wire 1 T! i2c_next_state [18] $end
$var wire 1 U! i2c_next_state [17] $end
$var wire 1 V! i2c_next_state [16] $end
$var wire 1 W! i2c_next_state [15] $end
$var wire 1 X! i2c_next_state [14] $end
$var wire 1 Y! i2c_next_state [13] $end
$var wire 1 Z! i2c_next_state [12] $end
$var wire 1 [! i2c_next_state [11] $end
$var wire 1 \! i2c_next_state [10] $end
$var wire 1 ]! i2c_next_state [9] $end
$var wire 1 ^! i2c_next_state [8] $end
$var wire 1 _! i2c_next_state [7] $end
$var wire 1 `! i2c_next_state [6] $end
$var wire 1 a! i2c_next_state [5] $end
$var wire 1 b! i2c_next_state [4] $end
$var wire 1 c! i2c_next_state [3] $end
$var wire 1 d! i2c_next_state [2] $end
$var wire 1 e! i2c_next_state [1] $end
$var wire 1 f! i2c_next_state [0] $end
$var reg 8 g! addr_reg [7:0] $end
$var wire 1 h! acquire_data_address $end
$var reg 8 i! data_reg [7:0] $end
$var reg 8 j! output_reg [7:0] $end
$var reg 1 k! SDA_input $end
$var wire 1 l! SDA_control $end
$var wire 1 m! ACK_control $end
$var wire 1 n! Data_control $end
$var reg 1 o! prev_val $end
$var reg 1 p! curr_val $end
$var wire 1 q! start_sign $end
$var wire 1 r! stop_sign $end
$var reg 1 s! start_received $end
$var reg 1 t! stop_received $end
$upscope $end
$upscope $end
$enddefinitions $end
#0
$dumpvars
0#
0$
1%
1Y
b0 Z
b0 [
b0 \
1]
0^
1_
bx e
b1 ?!
b0 g!
b0 i!
bx j!
0k!
xo!
xp!
xs!
xt!
b0 .
b1 /
b10 0
b11 1
b100 2
b101 3
b110 4
b111 5
b1000 6
b1001 7
b1010 8
b1011 9
b1100 :
b10100 ;
b10101 <
b11101 =
b0 g
b1 h
b10 i
b11 j
b100 k
b101 l
b110 m
b111 n
b1000 o
b1001 p
b1010 q
b1011 r
b1100 s
b1101 t
b1110 u
b1111 v
b10000 w
b10001 x
b10010 y
b10011 z
b10100 {
b10101 |
b10110 }
b10111 ~
b11000 !!
b11001 "!
b11010 #!
b11011 $!
b11100 %!
b11101 &!
b11110 '!
b11111 (!
b100000 )!
b100001 *!
b100010 +!
b100011 ,!
b100100 -!
b100101 .!
b100110 /!
1!
0"
z-
z,
z+
z*
z)
z(
z'
z&
1`
1a
0b
0c
0d
0f
xf!
xe!
0d!
0c!
0b!
0a!
0`!
0_!
0^!
0]!
0\!
0[!
0Z!
0Y!
0X!
0W!
0V!
0U!
0T!
0S!
0R!
0Q!
0P!
0O!
0N!
0M!
0L!
0K!
0J!
0I!
0H!
0G!
0F!
0E!
0D!
0C!
0B!
0A!
0@!
0h!
0l!
0m!
0n!
xq!
xr!
18!
17!
06!
05!
04!
13!
02!
01!
00!
1X
0W
0V
0U
1T
0S
1R
0Q
1P
0O
1N
0M
0L
0K
0J
0I
0H
0G
0F
1E
0D
0C
0B
1A
0@
0?
0>
z>!
z=!
z<!
z;!
z:!
z9!
$end
#10
0%
0X
08!
1#
1>
10!
0p!
b1 Z
b1111 e
0r!
#20
0#
0>
00!
#23
1$
1V
b1 \
b1 [
b10 \
#30
1#
1>
10!
0o!
b10 Z
b1110 e
0q!
#40
0#
0>
00!
#50
1#
1>
10!
b11 Z
b1101 e
#60
0#
0>
00!
#70
1#
1>
10!
b100 Z
b1100 e
#80
0#
0>
00!
#90
1#
1>
10!
b101 Z
b1011 e
#100
0#
0>
00!
#110
1#
1>
10!
b110 Z
b1010 e
#120
0#
0>
00!
#123
0$
0V
#130
1#
1>
10!
b111 Z
b1001 e
#140
0#
0>
00!
#150
1#
1>
10!
b1000 Z
b1000 e
#160
0#
0>
00!
#170
1#
1>
10!
b1001 Z
b111 e
#180
0#
0>
00!
#190
1#
1>
10!
b1010 Z
b110 e
#200
0#
0>
00!
#210
1#
1>
10!
b1011 Z
b101 e
#220
0#
0>
00!
#230
1#
1>
10!
b1100 Z
b100 e
#240
0#
0>
00!
#250
1#
1>
10!
b1101 Z
b11 e
#260
0#
0>
00!
#270
1#
1>
10!
b1110 Z
b10 e
#280
0#
0>
00!
#290
1#
1>
10!
b1111 Z
b1 e
#300
0#
0>
00!
#310
1#
1>
10!
b10000 Z
b0 e
1c
0_
1b
#320
0#
0>
00!
#330
1#
1>
10!
b10001 Z
#340
0#
0>
00!
#350
1#
1>
10!
b10010 Z
#360
0#
0>
00!
#370
1#
1>
10!
b10011 Z
#380
0#
0>
00!
#390
1#
1>
10!
b10100 Z
#400
0#
0>
00!
#410
1#
1>
10!
b10101 Z
#420
0#
0>
00!
#430
1#
1>
10!
b10110 Z
#440
0#
0>
00!
#450
1#
1>
10!
b10111 Z
#460
0#
0>
00!
#470
1#
1>
10!
b11000 Z
#480
0#
0>
00!
#490
1#
1>
10!
b11001 Z
#500
0#
0>
00!
#510
1#
1>
10!
b11010 Z
#520
0#
0>
00!
#530
1#
1>
10!
b11011 Z
#540
0#
0>
00!
#550
1#
1>
10!
b11100 Z
#560
0#
0>
00!
#570
1#
1>
10!
b11101 Z
#580
0#
0>
00!
#590
1#
1>
10!
b11110 Z
#600
0#
0>
00!
#610
1#
1>
10!
b11111 Z
#620
0#
0>
00!
#630
1#
1>
10!
b100000 Z
#640
0#
0>
00!
#650
1#
1>
10!
b100001 Z
#660
0#
0>
00!
#670
1#
1>
10!
b100010 Z
#680
0#
0>
00!
#690
1#
1>
10!
b100011 Z
#700
0#
0>
00!
#710
1#
1>
10!
b100100 Z
#720
0#
0>
00!
#730
1#
1>
10!
b100101 Z
#740
0#
0>
00!
#750
1#
1>
10!
b100110 Z
#760
0#
0>
00!
#770
1#
1>
10!
b100111 Z
#780
0#
0>
00!
#790
1#
1>
10!
b101000 Z
#800
0#
0>
00!
#810
1#
1>
10!
b101001 Z
#820
0#
0>
00!
#830
1#
1>
10!
b101010 Z
#840
0#
0>
00!
#850
1#
1>
10!
b101011 Z
#860
0#
0>
00!
#870
1#
1>
10!
b101100 Z
#880
0#
0>
00!
#890
1#
1>
10!
b101101 Z
#900
0#
0>
00!
#910
1#
1>
10!
b101110 Z
#920
0#
0>
00!
#930
1#
1>
10!
b101111 Z
#940
0#
0>
00!
#950
1#
1>
10!
b110000 Z
#960
0#
0>
00!
#970
1#
1>
10!
b110001 Z
#980
0#
0>
00!
#990
1#
1>
10!
b110010 Z
#1000
0#
0>
00!
#1010
1#
1>
10!
b110011 Z
#1020
0#
0>
00!
#1030
1#
1>
10!
b110100 Z
#1040
0#
0>
00!
#1050
1#
1>
10!
b110101 Z
#1060
0#
0>
00!
#1070
1#
1>
10!
b110110 Z
#1080
0#
0>
00!
#1090
1#
1>
10!
b110111 Z
#1100
0#
0>
00!
#1110
1#
1>
10!
b111000 Z
#1120
0#
0>
00!
#1130
1#
1>
10!
b111001 Z
#1140
0#
0>
00!
#1150
1#
1>
10!
b111010 Z
#1160
0#
0>
00!
#1170
1#
1>
10!
b111011 Z
#1180
0#
0>
00!
#1190
1#
1>
10!
b111100 Z
#1200
0#
0>
00!
#1210
1#
1>
10!
b111101 Z
#1220
0#
0>
00!
#1230
1#
1>
10!
b111110 Z
#1240
0#
0>
00!
#1250
1#
1>
10!
b111111 Z
#1260
0#
0>
00!
#1270
1#
1>
10!
b1000000 Z
#1280
0#
0>
00!
#1290
1#
1>
10!
b1000001 Z
#1300
0#
0>
00!
#1310
1#
1>
10!
b1000010 Z
#1320
0#
0>
00!
#1330
1#
1>
10!
b1000011 Z
#1340
0#
0>
00!
#1350
1#
1>
10!
b1000100 Z
#1360
0#
0>
00!
#1370
1#
1>
10!
b1000101 Z
#1380
0#
0>
00!
#1390
1#
1>
10!
b1000110 Z
#1400
0#
0>
00!
#1410
1#
1>
10!
b1000111 Z
#1420
0#
0>
00!
#1430
1#
1>
10!
b1001000 Z
#1440
0#
0>
00!
#1450
1#
1>
10!
b1001001 Z
#1460
0#
0>
00!
#1470
1#
1>
10!
b1001010 Z
#1480
0#
0>
00!
#1490
1#
1>
10!
b1001011 Z
#1500
0#
0>
00!
#1510
1#
1>
10!
b1001100 Z
#1520
0#
0>
00!
#1530
1#
1>
10!
b1001101 Z
#1540
0#
0>
00!
#1550
1#
1>
10!
b1001110 Z
#1560
0#
0>
00!
#1570
1#
1>
10!
b1001111 Z
#1580
0#
0>
00!
#1590
1#
1>
10!
b1010000 Z
#1600
0#
0>
00!
#1610
1#
1>
10!
b1010001 Z
#1620
0#
0>
00!
#1630
1#
1>
10!
b1010010 Z
#1640
0#
0>
00!
#1650
1#
1>
10!
b1010011 Z
#1660
0#
0>
00!
#1670
1#
1>
10!
b1010100 Z
#1680
0#
0>
00!
#1690
1#
1>
10!
b1010101 Z
#1700
0#
0>
00!
#1710
1#
1>
10!
b1010110 Z
#1720
0#
0>
00!
#1730
1#
1>
10!
b1010111 Z
#1740
0#
0>
00!
#1750
1#
1>
10!
b1011000 Z
#1760
0#
0>
00!
#1770
1#
1>
10!
b1011001 Z
#1780
0#
0>
00!
#1790
1#
1>
10!
b1011010 Z
#1800
0#
0>
00!
#1810
1#
1>
10!
b1011011 Z
#1820
0#
0>
00!
#1830
1#
1>
10!
b1011100 Z
#1840
0#
0>
00!
#1850
1#
1>
10!
b1011101 Z
#1860
0#
0>
00!
#1870
1#
1>
10!
b1011110 Z
#1880
0#
0>
00!
#1890
1#
1>
10!
b1011111 Z
#1900
0#
0>
00!
#1910
1#
1>
10!
b1100000 Z
#1920
0#
0>
00!
#1930
1#
1>
10!
b1100001 Z
#1940
0#
0>
00!
#1950
1#
1>
10!
b1100010 Z
#1960
0#
0>
00!
#1970
1#
1>
10!
b1100011 Z
#1980
0#
0>
00!
#1990
1#
1>
10!
b1100100 Z
#2000
0#
0>
00!
#2010
1#
1>
10!
b1100101 Z
#2020
0#
0>
00!
#2030
1#
1>
10!
b1100110 Z
#2040
0#
0>
00!
#2050
1#
1>
10!
b1100111 Z
#2060
0#
0>
00!
#2070
1#
1>
10!
b1101000 Z
#2080
0#
0>
00!
#2090
1#
1>
10!
b1101001 Z
#2100
0#
0>
00!
#2110
1#
1>
10!
b1101010 Z
#2120
0#
0>
00!
#2130
1#
1>
10!
b1101011 Z
#2140
0#
0>
00!
#2150
1#
1>
10!
b1101100 Z
#2160
0#
0>
00!
#2170
1#
1>
10!
b1101101 Z
#2180
0#
0>
00!
#2190
1#
1>
10!
b1101110 Z
#2200
0#
0>
00!
#2210
1#
1>
10!
b1101111 Z
#2220
0#
0>
00!
#2230
1#
1>
10!
b1110000 Z
#2240
0#
0>
00!
#2250
1#
1>
10!
b1110001 Z
#2260
0#
0>
00!
#2270
1#
1>
10!
b1110010 Z
#2280
0#
0>
00!
#2290
1#
1>
10!
b1110011 Z
#2300
0#
0>
00!
#2310
1#
1>
10!
b1110100 Z
#2320
0#
0>
00!
#2330
1#
1>
10!
b1110101 Z
#2340
0#
0>
00!
#2350
1#
1>
10!
b1110110 Z
#2360
0#
0>
00!
#2370
1#
1>
10!
b1110111 Z
#2380
0#
0>
00!
#2390
1#
1>
10!
b1111000 Z
#2400
0#
0>
00!
#2410
1#
1>
10!
b1111001 Z
#2420
0#
0>
00!
#2430
1#
1>
10!
b1111010 Z
#2440
0#
0>
00!
#2450
1#
1>
10!
b1111011 Z
#2460
0#
0>
00!
#2470
1#
1>
10!
b1111100 Z
#2480
0#
0>
00!
#2490
1#
1>
10!
b1111101 Z
#2500
0#
0>
00!
#2510
1#
1>
10!
b1111110 Z
#2520
0#
0>
00!
#2530
1#
1>
10!
b1111111 Z
#2540
0#
0>
00!
#2550
1#
1>
10!
b10000000 Z
#2560
0#
0>
00!
#2570
1#
1>
10!
b10000001 Z
#2580
0#
0>
00!
#2590
1#
1>
10!
b10000010 Z
#2600
0#
0>
00!
#2610
1#
1>
10!
b10000011 Z
#2620
0#
0>
00!
